{
  "or-eweb-heat-pump-water-heater": {
    "name": {
      "en": "Heat Pump Water Heater Program"
    },
    "url": {
      "en": "https://www.eweb.org/rebates-and-savings/residential-incentives-rebates-loans-and-conservation/heat-pump-water-heaters"
    },
    "authority": "or-eweb",
    "authority_type": "utility",
    "description": ""
  },
  "or-eweb-residential-ducted-heat-pump": {
    "name": {
      "en": "Residential Ducted Heat Pump Program"
    },
    "url": {
      "en": "https://www.eweb.org/rebates-and-savings/residential-incentives-rebates-loans-and-conservation/ducted-heat-pumps"
    },
    "authority": "or-eweb",
    "authority_type": "utility",
    "description": ""
  },
  "or-eweb-residential-ductless-heat-pump": {
    "name": {
      "en": "Residential Ductless Heat Pump Program"
    },
    "url": {
      "en": "https://www.eweb.org/rebates-and-savings/residential-incentives-rebates-loans-and-conservation/ductless-heat-pump"
    },
    "authority": "or-eweb",
    "authority_type": "utility",
    "description": ""
  },
  "or-eweb-residential-insulation-air-sealing": {
    "name": {
      "en": "Residential Insulation, Air Sealing, and Windows Program"
    },
    "url": {
      "en": "https://www.eweb.org/rebates-and-savings/residential-incentives-rebates-loans-and-conservation/insulation-air-sealing-and-windows"
    },
    "authority": "or-eweb",
    "authority_type": "utility",
    "description": ""
  },
  "or-portland-general-electric-p2p": {
    "name": {
      "en": "Power to the People PDX (P2P)"
    },
    "url": {
      "en": "https://www.aaah.org/power-to-the-people-pdx"
    },
    "authority": "or-portland-general-electric",
    "authority_type": "utility",
    "description": ""
  },
  "or_centralElectricCooperative_residentialRebates": {
    "name": {
      "en": "Residential Rebates"
    },
    "url": {
      "en": "https://www.central.coop/rebates"
    },
    "authority": "or-central-electric-cooperative",
    "authority_type": "utility",
    "description": ""
  },
  "or_cityOfAshland_residentialIncentives": {
    "name": {
      "en": "Residential Incentives"
    },
    "url": {
      "en": "https://ashlandoregon.gov/584/Residential-Incentives"
    },
    "authority": "or-city-of-ashland",
    "authority_type": "utility",
    "description": ""
  },
  "or_cityOfMcminnville_energyEfficiencyRebatesAndIncentives": {
    "name": {
      "en": "Energy Efficiency Rebates & Incentives"
    },
    "url": {
      "en": "https://www.mc-power.com/energy-efficiency/energy-efficiency-rebates-incentives/"
    },
    "authority": "or-city-of-mc-minnville",
    "authority_type": "utility",
    "description": ""
  },
  "or_cityOfMonmouth_residentialEnergyEfficiencyRebates": {
    "name": {
      "en": "Residential Energy Efficiency Rebates"
    },
    "url": {
      "en": "https://www.ci.monmouth.or.us/pview.aspx?id=55053&catid=0"
    },
    "authority": "or-city-of-monmouth",
    "authority_type": "utility",
    "description": ""
  },
  "or_columbiaRiverPud_waysToSaveAtHome": {
    "name": {
      "en": "Ways to Save At Home"
    },
    "url": {
      "en": "https://www.crpud.net/ways-to-save/at-home/"
    },
    "authority": "or-columbia-river-pud",
    "authority_type": "utility",
    "description": ""
  },
  "or_consumersPower_energyEfficiencyRebates": {
    "name": {
      "en": "Energy Efficiency Rebates"
    },
    "url": {
      "en": "https://www.directefficiency.com/cpi-rebates/"
    },
    "authority": "or-consumers-power",
    "authority_type": "utility",
    "description": "Consumers Power Energy Efficiency Rebates"
  },
  "or_emeraldPeople'SUtilityDistrict_residentialIncentivePrograms": {
    "name": {
      "en": "Residential Incentive Programs"
    },
    "url": {
      "en": "https://www.epud.org/energy-efficiency/energy-incentive-programs/residential-incentive-programs/"
    },
    "authority": "or-emerald-people-s-utility-district",
    "authority_type": "utility",
    "description": ""
  },
  "or_energyTrustOfOregon_energyTrustOfOregon": {
    "name": {
      "en": "Energy Trust of Oregon"
    },
    "url": {
      "en": "https://www.energytrust.org/residential/incentives"
    },
    "authority": "or-energy-trust-of-oregon",
    "authority_type": "state"
  },
  "or_energyTrustOfOregon_extendedCapacityHeatPump": {
    "name": {
      "en": "Extended Capacity Heat Pump"
    },
    "url": {
      "en": "https://www.energytrust.org/residential/incentives"
    },
    "authority": "or-energy-trust-of-oregon",
    "authority_type": "state"
  },
  "or_energyTrustOfOregon_savingsWithinReach": {
    "name": {
      "en": "Savings Within Reach"
    },
    "url": {
      "en": "https://www.energytrust.org/residential/incentives"
    },
    "authority": "or-energy-trust-of-oregon",
    "authority_type": "state"
  },
  "or_idahoPower_heatingAndCoolingEfficiencyProgram": {
    "name": {
      "en": "Heating and Cooling Efficiency Program"
    },
    "url": {
      "en": "https://www.idahopower.com/energy-environment/ways-to-save/savings-for-your-home/rebates-and-offers/heating-and-cooling-efficiency-program/"
    },
    "authority": "or-idaho-power",
    "authority_type": "utility",
    "description": ""
  },
  "or_midstateElectricCooperative_residentialConservationIncentives": {
    "name": {
      "en": "Residential Conservation Incentives"
    },
    "url": {
      "en": "https://www.midstateelectric.coop/residential"
    },
    "authority": "or-midstate-electric-cooperative",
    "authority_type": "utility",
    "description": ""
  },
  "or_oregonHousingAndCommunityServices_stateHomeOilWeatherizationSHOWProgram": {
    "name": {
      "en": "State Home Oil Weatherization (SHOW) Program"
    },
    "url": {
      "en": "https://www.oregon.gov/ohcs/energy-weatherization/Documents/factsheets/factsheet-show.pdf"
    },
    "authority": "or-oregon-housing-and-community-services",
    "authority_type": "state",
    "description": "Eligible dwellings must receive their primary heating fuel from a fuel oil dealer. Cash payments are awarded by a two-tier system to allow for varied income eligibility."
  },
  "or_pacificPower_extendedCapacityHeatPumpRegionalPromotion": {
    "name": {
      "en": "Extended Capacity Heat Pump Regional Promotion"
    },
    "url": {
      "en": "https://www.energytrust.org/residential/incentives/furnace-and-heat-pump/all"
    },
    "authority": "or-pacific-power",
    "authority_type": "utility"
  },
  "or_pacificPower_heatPumpRegionalPromotion": {
    "name": {
      "en": "Heat Pump Regional Promotion"
    },
    "url": {
      "en": "https://www.energytrust.org/residential/incentives/furnace-and-heat-pump/all"
    },
    "authority": "or-pacific-power",
    "authority_type": "utility"
  },
  "or_pacificPower_pacificPowerRebates": {
    "name": {
      "en": "Pacific Power Rebates"
    },
    "url": {
      "en": "https://www.pacificpower.net/savings-energy-choices/electric-vehicles/home-charger-rebates.html"
    },
    "authority": "or-pacific-power",
    "authority_type": "utility"
  },
  "or_pacificPower_solarForYourHome": {
    "name": {
      "en": "Solar for your Home"
    },
    "url": {
      "en": "https://www.energytrust.org/incentives/solar-for-your-home"
    },
    "authority": "or-pacific-power",
    "authority_type": "utility"
  },
  "or_pacificPower_solarWithinReach": {
    "name": {
      "en": "Solar Within Reach"
    },
    "url": {
      "en": "https://www.energytrust.org/incentives/solar-within-reach"
    },
    "authority": "or-pacific-power",
    "authority_type": "utility"
  },
  "or_portlandGeneralElectric_pGESmartChargingProgram": {
    "name": {
      "en": "PGE Smart Charging Program"
    },
    "url": {
      "en": "https://portlandgeneral.com/energy-choices/electric-vehicles-charging/charging-your-ev/charging-your-ev-at-home"
    },
    "authority": "or-portland-general-electric",
    "authority_type": "utility"
  },
  "or_portlandGeneralElectric_pGESmartThermostatProgram": {
    "name": {
      "en": "PGE Smart Thermostat Program"
    },
    "url": {
      "en": "https://portlandgeneral.com/save-money/save-money-home/smart-thermostat-program"
    },
    "authority": "or-portland-general-electric",
    "authority_type": "utility"
  },
  "or_portlandGeneralElectric_solarForYourHome": {
    "name": {
      "en": "Solar for your Home"
    },
    "url": {
      "en": "https://www.energytrust.org/incentives/solar-for-your-home"
    },
    "authority": "or-portland-general-electric",
    "authority_type": "utility"
  },
  "or_portlandGeneralElectric_solarWithinReach": {
    "name": {
      "en": "Solar Within Reach"
    },
    "url": {
      "en": "https://www.energytrust.org/incentives/solar-within-reach"
    },
    "authority": "or-portland-general-electric",
    "authority_type": "utility"
  },
  "or_salemElectric_applianceIncentives": {
    "name": {
      "en": "Appliance Incentives"
    },
    "url": {
      "en": "https://www.salemelectric.com/energy-efficiency/incentives/"
    },
    "authority": "or-salem-electric",
    "authority_type": "utility",
    "description": "Incentives for water heaters, clothes dryers, and washers"
  },
  "or_salemElectric_electricVehicleIncentives": {
    "name": {
      "en": "Electric Vehicle Incentives"
    },
    "url": {
      "en": "https://www.salemelectric.com/energy-efficiency/electric-vehicles/"
    },
    "authority": "or-salem-electric",
    "authority_type": "utility",
    "description": ""
  },
  "or_salemElectric_heatPumpProgram": {
    "name": {
      "en": "Heat Pump Program"
    },
    "url": {
      "en": "https://www.salemelectric.com/energy-efficiency/incentives/"
    },
    "authority": "or-salem-electric",
    "authority_type": "utility",
    "description": ""
  },
  "or_salemElectric_smartThermostatIncentive": {
    "name": {
      "en": "Smart Thermostat Incentive"
    },
    "url": {
      "en": "https://www.salemelectric.com/energy-efficiency/incentives/"
    },
    "authority": "or-salem-electric",
    "authority_type": "utility",
    "description": ""
  },
  "or_salemElectric_solarIncentives": {
    "name": {
      "en": "Solar Incentives"
    },
    "url": {
      "en": "https://www.salemelectric.com/energy-efficiency/solar-information/"
    },
    "authority": "or-salem-electric",
    "authority_type": "utility",
    "description": ""
  },
  "or_salemElectric_weatherizationProgram": {
    "name": {
      "en": "Weatherization Program"
    },
    "url": {
      "en": "https://www.salemelectric.com/energy-efficiency/incentives/"
    },
    "authority": "or-salem-electric",
    "authority_type": "utility",
    "description": ""
  },
  "or_tillamookPeople'SUtilityDistrict_residentialHeatPumpProgram": {
    "name": {
      "en": "Residential Heat Pump Program"
    },
    "url": {
      "en": "https://www.tpud.org/ways-to-save/heat-pump-programs/residential-heat-pump-program/"
    },
    "authority": "or-tillamook-people-s-utility-district",
    "authority_type": "utility",
    "description": ""
  },
  "or_tillamookPeople'SUtilityDistrict_residentialRebates": {
    "name": {
      "en": "Residential Rebates"
    },
    "url": {
      "en": "https://www.tpud.org/ways-to-save/appliance-water-heater-rebates/"
    },
    "authority": "or-tillamook-people-s-utility-district",
    "authority_type": "utility",
    "description": ""
  }
}
