[
  {
    "id": "IN-1",
    "payment_methods": [
      "account_credit"
    ],
    "items": [
      "non_heat_pump_water_heater",
      "heat_pump_water_heater"
    ],
    "program": "in-jay-county-remc-water-heater",
    "amount": {
      "type": "dollar_amount",
      "number": 200,
      "minimum": 125,
      "maximum": 200
    },
    "owner_status": [
      "homeowner"
    ],
    "short_description": {
      "en": "Up to $200 bill credit on energy efficient water heaters in new structures or replacement of gas water heaters with an electric model.",
      "es": "Crédito de factura de hasta $200 en calentadores de agua energéticamente eficientes en estructuras nuevas o reemplazo de calentadores de agua a gas con un modelo eléctrico."
    },
    "url": {
      "en": "https://www.jayremc.com/water-heater-rebate"
    }
  },
  {
    "id": "IN-2",
    "payment_methods": [
      "rebate"
    ],
    "items": [
      "ducted_heat_pump"
    ],
    "program": "in-carroll-white-heat-pump",
    "amount": {
      "type": "dollar_amount",
      "number": 750,
      "minimum": 300,
      "maximum": 750
    },
    "owner_status": [
      "homeowner"
    ],
    "short_description": {
      "en": "Up to $750 rebate on an air source heat pump.",
      "es": "Reembolso de hasta $750 en una bomba de calor de fuente de aire."
    },
    "url": {
      "en": "https://www.cwremc.coop/programs/rebates/heat-pump-rebates/"
    }
  },
  {
    "id": "IN-3",
    "payment_methods": [
      "rebate"
    ],
    "items": [
      "geothermal_heating_installation"
    ],
    "program": "in-carroll-white-heat-pump",
    "amount": {
      "type": "dollar_amount",
      "number": 1500,
      "minimum": 500,
      "maximum": 1500
    },
    "owner_status": [
      "homeowner"
    ],
    "short_description": {
      "en": "Up to $1,500 rebate on a geothermal heat pump.",
      "es": "Reembolso de hasta $1,500 en una bomba de calor geotérmica."
    },
    "url": {
      "en": "https://www.cwremc.coop/programs/rebates/heat-pump-rebates/"
    }
  },
  {
    "id": "IN-4",
    "payment_methods": [
      "pos_rebate"
    ],
    "items": [
      "smart_thermostat"
    ],
    "program": "in-sei-rebates",
    "amount": {
      "type": "percent",
      "number": 1,
      "maximum": 150
    },
    "owner_status": [
      "homeowner"
    ],
    "short_description": {
      "en": "Free ecobee smart thermostat.",
      "es": "Termostato inteligente ecobee gratis."
    },
    "url": {
      "en": "https://www.seiremc.com/rebates"
    }
  },
  {
    "id": "IN-5",
    "payment_methods": [
      "rebate"
    ],
    "items": [
      "ducted_heat_pump",
      "ductless_heat_pump",
      "duct_sealing"
    ],
    "program": "in-duke-energy-smart-saver",
    "amount": {
      "type": "dollar_amount",
      "number": 800,
      "minimum": 500,
      "maximum": 800
    },
    "owner_status": [
      "homeowner"
    ],
    "short_description": {
      "en": "Up to $500 rebate for air-source heat pumps with required duct sealing. Up to $300 bonus for early retirement of old system.",
      "es": "Reembolso de hasta $500 para bombas de calor aerotérmicas con sellado de conductos obligatorio. Bonificación de hasta $300 por retiro anticipado del sistema antiguo."
    },
    "url": {
      "en": "https://www.duke-energy.com/home/products/smart-saver"
    }
  },
  {
    "id": "IN-6",
    "payment_methods": [
      "rebate"
    ],
    "items": [
      "smart_thermostat"
    ],
    "program": "in-duke-energy-smart-saver",
    "amount": {
      "type": "dollar_amount",
      "number": 65,
      "maximum": 65
    },
    "owner_status": [
      "homeowner"
    ],
    "short_description": {
      "en": "Up to $65 bonus on smart thermostat purchased with corresponding HVAC equipment upgrade.",
      "es": "Bono de hasta $65 en termostato inteligente comprado con la actualización correspondiente del equipo HVAC."
    },
    "url": {
      "en": "https://www.duke-energy.com/home/products/smart-saver"
    }
  },
  {
    "id": "IN-7",
    "payment_methods": [
      "rebate"
    ],
    "items": [
      "duct_sealing",
      "geothermal_heating_installation"
    ],
    "program": "in-duke-energy-smart-saver",
    "amount": {
      "type": "dollar_amount",
      "number": 700,
      "minimum": 500,
      "maximum": 700
    },
    "owner_status": [
      "homeowner"
    ],
    "short_description": {
      "en": "Up to $500 rebate for ground-source heat pumps with required duct sealing. Up to $200 bonus for early retirement of old system.",
      "es": "Reembolso de hasta $500 para bombas de calor geotérmicas con el sellado de conductos requerido. Bonificación de hasta $200 por la retirada anticipada del sistema antiguo."
    },
    "url": {
      "en": "https://www.duke-energy.com/home/products/smart-saver"
    }
  },
  {
    "id": "IN-8",
    "payment_methods": [
      "rebate"
    ],
    "items": [
      "heat_pump_water_heater"
    ],
    "program": "in-duke-energy-smart-saver",
    "amount": {
      "type": "dollar_amount",
      "number": 350,
      "maximum": 350
    },
    "owner_status": [
      "homeowner"
    ],
    "short_description": {
      "en": "Receive $350 rebate for a qualifying heat pump water heater.",
      "es": "Reciba un reembolso de $350 por un calentador de agua con bomba de calor calificado."
    },
    "url": {
      "en": "https://www.duke-energy.com/home/products/smart-saver"
    }
  },
  {
    "id": "IN-9",
    "payment_methods": [
      "rebate"
    ],
    "items": [
      "air_sealing",
      "attic_or_roof_insulation"
    ],
    "program": "in-duke-energy-smart-saver",
    "amount": {
      "type": "dollar_amount",
      "number": 350,
      "maximum": 350
    },
    "owner_status": [
      "homeowner"
    ],
    "short_description": {
      "en": "Up to $350 rebate for attic insulation and attic air sealing.",
      "es": "Reembolso de hasta $350 por aislamiento y sellado de aire del ático."
    },
    "url": {
      "en": "https://www.duke-energy.com/home/products/smart-saver"
    }
  },
  {
    "id": "IN-10",
    "payment_methods": [
      "assistance_program"
    ],
    "items": [
      "energy_audit"
    ],
    "program": "in-indiana-michigan-electric-ideas",
    "amount": {
      "type": "percent",
      "number": 1
    },
    "owner_status": [
      "homeowner",
      "renter"
    ],
    "short_description": {
      "en": "Income-qualified customers can schedule a no-cost home energy checkup.",
      "es": "Los clientes que califican según sus ingresos pueden programar una revisión de energía del hogar sin costo."
    },
    "low_income": "in-indiana-michigan-power-low-income",
    "url": {
      "en": "https://electricideas.com/at-home/energy-saving-programs/home-energy-checkup/"
    }
  },
  {
    "id": "IN-11",
    "payment_methods": [
      "assistance_program",
      "rebate"
    ],
    "items": [
      "wall_insulation",
      "other_weatherization",
      "other_insulation",
      "floor_insulation",
      "efficiency_rebates",
      "duct_sealing",
      "crawlspace_insulation",
      "basement_insulation",
      "attic_or_roof_insulation",
      "air_sealing"
    ],
    "program": "in-indiana-michigan-electric-ideas",
    "amount": {
      "type": "percent",
      "number": 1,
      "maximum": 4000
    },
    "owner_status": [
      "homeowner",
      "renter"
    ],
    "short_description": {
      "en": "For qualifying homes, rebate of up to 100% of the cost (up to $4,000) to weatherproof the home.",
      "es": "Para viviendas calificadas, reembolso de hasta el 100% del costo (hasta $4,000) para impermeabilizar la vivienda."
    },
    "low_income": "in-indiana-michigan-power-low-income",
    "url": {
      "en": "https://electricideas.com/at-home/energy-saving-programs/home-energy-checkup/"
    }
  },
  {
    "id": "IN-12",
    "payment_methods": [
      "pos_rebate"
    ],
    "items": [
      "smart_thermostat"
    ],
    "program": "in-indiana-michigan-electric-ideas",
    "amount": {
      "type": "dollar_amount",
      "number": 25
    },
    "owner_status": [
      "homeowner"
    ],
    "short_description": {
      "en": "$25 rebate for smart thermostats in homes with electric heating only.",
      "es": "Reembolso de $25 para termostatos inteligentes en hogares con calefacción únicamente eléctrica."
    },
    "url": {
      "en": "https://electricideas.com/at-home/energy-saving-programs/home-energy-checkup/"
    }
  },
  {
    "id": "IN-13",
    "eligible_geo_group": "in-wabash-valley-power-alliance",
    "payment_methods": [
      "rebate"
    ],
    "items": [
      "smart_thermostat"
    ],
    "program": "in-power-moves",
    "amount": {
      "type": "dollar_amount",
      "number": 75,
      "maximum": 75
    },
    "owner_status": [
      "homeowner",
      "renter"
    ],
    "short_description": {
      "en": "$75 rebate for replacing a non Wi-Fi thermostat with Wi-Fi thermostat.",
      "es": "Reembolso de $75 por reemplazar un termostato sin Wi-Fi por un termostato con Wi-Fi."
    },
    "start_date": "2025-01-01",
    "end_date": "2025-12-31",
    "url": {
      "en": "https://www.powermoves.com"
    }
  },
  {
    "id": "IN-14",
    "eligible_geo_group": "in-wabash-valley-power-alliance",
    "payment_methods": [
      "rebate"
    ],
    "items": [
      "geothermal_heating_installation"
    ],
    "program": "in-power-moves",
    "amount": {
      "type": "dollar_amount",
      "number": 2000,
      "minimum": 250,
      "maximum": 2000
    },
    "owner_status": [
      "homeowner"
    ],
    "short_description": {
      "en": "Up to $2000 rebate on a closed loop geothermal heat pump system.",
      "es": "Reembolso de hasta $2000 en un sistema de bomba de calor geotérmica de circuito cerrado."
    },
    "start_date": "2025-01-01",
    "end_date": "2025-12-31",
    "url": {
      "en": "https://www.powermoves.com"
    }
  },
  {
    "id": "IN-15",
    "eligible_geo_group": "in-wabash-valley-power-alliance",
    "payment_methods": [
      "rebate"
    ],
    "items": [
      "geothermal_heating_installation"
    ],
    "program": "in-power-moves",
    "amount": {
      "type": "dollar_amount",
      "number": 1000,
      "minimum": 250,
      "maximum": 1000
    },
    "owner_status": [
      "homeowner"
    ],
    "short_description": {
      "en": "Up to $1000 rebate on an open loop geothermal heat pump system.",
      "es": "Reembolso de hasta $1000 en un sistema de bomba de calor geotérmica de circuito abierto."
    },
    "start_date": "2025-01-01",
    "end_date": "2025-12-31",
    "url": {
      "en": "https://www.powermoves.com"
    }
  },
  {
    "id": "IN-16",
    "eligible_geo_group": "in-wabash-valley-power-alliance",
    "payment_methods": [
      "rebate"
    ],
    "items": [
      "heat_pump_water_heater"
    ],
    "program": "in-power-moves",
    "amount": {
      "type": "dollar_amount",
      "number": 800,
      "maximum": 800
    },
    "owner_status": [
      "homeowner"
    ],
    "short_description": {
      "en": "Up to $800 rebate on a heat pump water heater.",
      "es": "Reembolso de hasta $800 en un calentador de agua con bomba de calor."
    },
    "start_date": "2025-01-01",
    "end_date": "2025-12-31",
    "url": {
      "en": "https://www.powermoves.com"
    }
  },
  {
    "id": "IN-17",
    "payment_methods": [
      "rebate"
    ],
    "items": [
      "duct_sealing"
    ],
    "program": "in-duke-energy-smart-saver",
    "amount": {
      "type": "dollar_amount",
      "number": 100,
      "maximum": 100
    },
    "owner_status": [
      "homeowner"
    ],
    "short_description": {
      "en": "Up to $100 rebate for duct sealing. Must reduce duct leakage by at least 12%.",
      "es": "Reembolso de hasta $100 por sellado de conductos. Debe reducir las fugas en los conductos al menos un 12 %."
    },
    "url": {
      "en": "https://www.duke-energy.com/home/products/smart-saver"
    }
  },
  {
    "id": "IN-18",
    "eligible_geo_group": "in-wabash-valley-power-alliance",
    "payment_methods": [
      "rebate"
    ],
    "items": [
      "ductless_heat_pump",
      "ducted_heat_pump"
    ],
    "program": "in-power-moves",
    "amount": {
      "type": "dollar_amount",
      "number": 1800,
      "minimum": 250,
      "maximum": 1800
    },
    "owner_status": [
      "homeowner"
    ],
    "short_description": {
      "en": "$500 rebate on a dual fuel heat pump.",
      "es": "Reembolso de $500 en una bomba de calor de combustible dual."
    },
    "start_date": "2025-01-01",
    "end_date": "2025-12-31",
    "url": {
      "en": "https://www.powermoves.com"
    }
  },
  {
    "id": "IN-19",
    "eligible_geo_group": "in-wabash-valley-power-alliance",
    "payment_methods": [
      "rebate"
    ],
    "items": [
      "ductless_heat_pump",
      "ducted_heat_pump"
    ],
    "program": "in-power-moves",
    "amount": {
      "type": "dollar_amount",
      "number": 800,
      "minimum": 250,
      "maximum": 800
    },
    "owner_status": [
      "homeowner"
    ],
    "short_description": {
      "en": "Up to $800 rebate on an air source (partial-home) heat pump. Higher rebate for a cold climate heat pumps.",
      "es": "Hasta $800 de descuento en una bomba de calor aerotérmica (para uso residencial parcial). Descuento mayor para bombas de calor para climas fríos."
    },
    "start_date": "2025-01-01",
    "end_date": "2025-12-31",
    "url": {
      "en": "https://www.powermoves.com"
    }
  },
  {
    "id": "IN-20",
    "payment_methods": [
      "rebate"
    ],
    "items": [
      "ducted_heat_pump",
      "ductless_heat_pump"
    ],
    "program": "in-noble-remc-residential-rebates",
    "amount": {
      "type": "dollars_per_unit",
      "number": 150,
      "unit": "ton",
      "maximum": 1500
    },
    "owner_status": [
      "homeowner"
    ],
    "short_description": {
      "en": "$150 per ton rebate on air-source heat pumps.",
      "es": "Descuento de $150 por tonelada en bombas de calor de fuente de aire."
    },
    "url": {
      "en": "https://nobleremc.com/rebates"
    }
  },
  {
    "id": "IN-21",
    "eligible_geo_group": "in-wabash-valley-power-alliance",
    "payment_methods": [
      "rebate"
    ],
    "items": [
      "ductless_heat_pump",
      "ducted_heat_pump"
    ],
    "program": "in-power-moves",
    "amount": {
      "type": "dollar_amount",
      "number": 1800,
      "minimum": 250,
      "maximum": 1800
    },
    "owner_status": [
      "homeowner"
    ],
    "short_description": {
      "en": "Up to $1,800 rebate on an air source (whole-home) heat pump. Higher rebate for a cold climate heat pumps.",
      "es": "Hasta $1,800 de descuento en una bomba de calor de aire (para toda la casa). Descuento mayor para bombas de calor en climas fríos."
    },
    "start_date": "2025-01-01",
    "end_date": "2025-12-31",
    "url": {
      "en": "https://www.powermoves.com"
    }
  },
  {
    "id": "IN-22",
    "payment_methods": [
      "rebate"
    ],
    "items": [
      "heat_pump_water_heater"
    ],
    "program": "in-noble-remc-residential-rebates",
    "amount": {
      "type": "percent",
      "number": 1
    },
    "owner_status": [
      "homeowner"
    ],
    "short_description": {
      "en": "FREE water heater for new homes; below-cost heat pump water heater when purchased through Noble REMC. Installation and wiring rebates up to $100.",
      "es": "Calentador de agua GRATIS para casas nuevas; calentador de agua con bomba de calor a bajo costo al comprar a través de Noble REMC. Reembolsos de hasta $100 en instalación y cableado."
    },
    "url": {
      "en": "https://nobleremc.com/rebates"
    }
  },
  {
    "id": "IN-23",
    "payment_methods": [
      "pos_rebate"
    ],
    "items": [
      "heat_pump_water_heater"
    ],
    "program": "in-indiana-michigan-electric-ideas",
    "amount": {
      "type": "dollar_amount",
      "number": 75
    },
    "owner_status": [
      "homeowner"
    ],
    "short_description": {
      "en": "$75 rebate for efficient electric water heaters.",
      "es": "Reembolso de $75 para calentadores de agua eléctricos eficientes."
    },
    "url": {
      "en": "https://electricideas.com/at-home/energy-saving-programs/home-energy-checkup/"
    }
  },
  {
    "id": "IN-24",
    "payment_methods": [
      "rebate"
    ],
    "items": [
      "electric_vehicle_charger"
    ],
    "program": "in-carroll-white-ev-charger",
    "amount": {
      "type": "percent",
      "number": 0.5,
      "maximum": 300
    },
    "owner_status": [
      "homeowner",
      "renter"
    ],
    "short_description": {
      "en": "Rebate for 50% of the cost of a home charging unit, up to $300. Must enroll in a time of use rate plan.",
      "es": "Reembolso del 50% del costo de un cargador doméstico, hasta $300. Debe suscribirse a un plan de tarifa por tiempo de uso."
    },
    "url": {
      "en": "https://www.cwremc.coop/programs/rebates/electric-vehicle-home-charging-program/"
    }
  },
  {
    "id": "IN-25",
    "payment_methods": [
      "assistance_program"
    ],
    "items": [
      "air_sealing",
      "attic_or_roof_insulation",
      "basement_insulation",
      "efficiency_rebates",
      "energy_audit",
      "floor_insulation",
      "other_heat_pump",
      "other_insulation",
      "other_weatherization",
      "duct_sealing",
      "ducted_heat_pump",
      "ductless_heat_pump",
      "wall_insulation"
    ],
    "program": "in_indianaOfficeOfEnergyDevelopment_indianaEnergySaverProgram",
    "amount": {
      "type": "percent",
      "number": 1,
      "maximum": 18000
    },
    "owner_status": [
      "homeowner"
    ],
    "short_description": {
      "en": "100% of project cost, up to $18,000 for income-qualified residents to make qualified home updates that provide 35%+ modeled energy savings.",
      "es": "100% del costo del proyecto, hasta $18,000 para residentes que califican en términos de ingresos para realizar actualizaciones calificadas en el hogar que brinden ahorros de energía modelados de más del 35%."
    },
    "paused": true,
    "low_income": "in-state-homes-program",
    "url": {
      "en": "https://indianaenergysaver.com"
    }
  },
  {
    "id": "IN-26",
    "payment_methods": [
      "pos_rebate"
    ],
    "items": [
      "air_sealing",
      "attic_or_roof_insulation",
      "basement_insulation",
      "efficiency_rebates",
      "energy_audit",
      "floor_insulation",
      "other_heat_pump",
      "other_insulation",
      "other_weatherization",
      "duct_sealing",
      "ducted_heat_pump",
      "ductless_heat_pump",
      "wall_insulation"
    ],
    "program": "in_indianaOfficeOfEnergyDevelopment_indianaEnergySaverProgram",
    "amount": {
      "type": "percent",
      "number": 0.5,
      "maximum": 4000
    },
    "owner_status": [
      "homeowner"
    ],
    "short_description": {
      "en": "50% of project cost, up to $4,000 discount from a qualified contractor, based on modeled energy savings, for home efficiency upgrades.",
      "es": "50% del costo del proyecto, hasta $4,000 de descuento de un contratista calificado, basado en ahorros de energía modelados, para mejoras de eficiencia en el hogar."
    },
    "paused": true,
    "url": {
      "en": "https://indianaenergysaver.com"
    }
  },
  {
    "id": "IN-27",
    "payment_methods": [
      "pos_rebate"
    ],
    "items": [
      "heat_pump_water_heater"
    ],
    "program": "in_indianaOfficeOfEnergyDevelopment_indianaEnergySaverProgram",
    "amount": {
      "type": "percent",
      "number": 0.5,
      "maximum": 1750
    },
    "owner_status": [
      "homeowner"
    ],
    "short_description": {
      "en": "50% of project cost, up to $1,750 discount for an ENERGY STAR-certified heat pump water heater, for moderate income residents.",
      "es": "50% del costo del proyecto, hasta $1,750 de descuento para un calentador de agua con bomba de calor con certificación ENERGY STAR, para residentes con ingresos moderados."
    },
    "paused": true,
    "low_income": "in-state-hear-program",
    "url": {
      "en": "https://indianaenergysaver.com"
    }
  },
  {
    "id": "IN-28",
    "payment_methods": [
      "pos_rebate"
    ],
    "items": [
      "heat_pump_water_heater"
    ],
    "program": "in_indianaOfficeOfEnergyDevelopment_indianaEnergySaverProgram",
    "amount": {
      "type": "percent",
      "number": 1,
      "maximum": 1750
    },
    "owner_status": [
      "homeowner"
    ],
    "short_description": {
      "en": "100% of project cost, up to $1,750 discount for an ENERGY STAR-certified heat pump water heater, for income-qualified residents.",
      "es": "100% del costo del proyecto, hasta $1,750 de descuento para un calentador de agua con bomba de calor con certificación ENERGY STAR, para residentes que califican según sus ingresos."
    },
    "paused": true,
    "low_income": "in-state-homes-program",
    "url": {
      "en": "https://indianaenergysaver.com"
    }
  },
  {
    "id": "IN-29",
    "payment_methods": [
      "pos_rebate"
    ],
    "items": [
      "ducted_heat_pump",
      "ductless_heat_pump"
    ],
    "program": "in_indianaOfficeOfEnergyDevelopment_indianaEnergySaverProgram",
    "amount": {
      "type": "percent",
      "number": 1,
      "maximum": 8000
    },
    "owner_status": [
      "homeowner"
    ],
    "short_description": {
      "en": "100% of project cost, up to $8,000 discount for an ENERGY STAR-certified heat pump for space heating and cooling, for income-qualified residents.",
      "es": "100% del costo del proyecto, hasta $8,000 de descuento para una bomba de calor con certificación ENERGY STAR para calefacción y refrigeración de espacios, para residentes que califican según sus ingresos."
    },
    "paused": true,
    "low_income": "in-state-homes-program",
    "url": {
      "en": "https://indianaenergysaver.com"
    }
  },
  {
    "id": "IN-30",
    "payment_methods": [
      "pos_rebate"
    ],
    "items": [
      "ducted_heat_pump",
      "ductless_heat_pump"
    ],
    "program": "in_indianaOfficeOfEnergyDevelopment_indianaEnergySaverProgram",
    "amount": {
      "type": "percent",
      "number": 0.5,
      "maximum": 8000
    },
    "owner_status": [
      "homeowner"
    ],
    "short_description": {
      "en": "50% of project cost, up to $8,000 discount for an ENERGY STAR-certified heat pump for space heating and cooling, for moderate income residents.",
      "es": "50% del costo del proyecto, hasta $8,000 de descuento para una bomba de calor con certificación ENERGY STAR para calefacción y refrigeración de espacios, para residentes con ingresos moderados."
    },
    "paused": true,
    "low_income": "in-state-hear-program",
    "url": {
      "en": "https://indianaenergysaver.com"
    }
  },
  {
    "id": "IN-31",
    "payment_methods": [
      "pos_rebate"
    ],
    "items": [
      "heat_pump_clothes_dryer"
    ],
    "program": "in_indianaOfficeOfEnergyDevelopment_indianaEnergySaverProgram",
    "amount": {
      "type": "percent",
      "number": 0.5,
      "maximum": 840
    },
    "owner_status": [
      "homeowner",
      "renter"
    ],
    "short_description": {
      "en": "50% of project cost, up to $840 discount for an ENERGY STAR-certified heat pump clothes dryer, for moderate income residents.",
      "es": "50% del costo del proyecto, hasta $840 de descuento para una secadora de ropa con bomba de calor con certificación ENERGY STAR, para residentes con ingresos moderados."
    },
    "paused": true,
    "low_income": "in-state-hear-program",
    "url": {
      "en": "https://indianaenergysaver.com"
    }
  },
  {
    "id": "IN-32",
    "payment_methods": [
      "pos_rebate"
    ],
    "items": [
      "heat_pump_clothes_dryer"
    ],
    "program": "in_indianaOfficeOfEnergyDevelopment_indianaEnergySaverProgram",
    "amount": {
      "type": "percent",
      "number": 1,
      "maximum": 840
    },
    "owner_status": [
      "homeowner",
      "renter"
    ],
    "short_description": {
      "en": "100% of project cost, up to $840 discount for an ENERGY STAR-certified heat pump clothes dryer, for income-qualified residents.",
      "es": "100% del costo del proyecto, hasta $840 de descuento para una secadora de ropa con bomba de calor con certificación ENERGY STAR, para residentes que califican según sus ingresos."
    },
    "paused": true,
    "low_income": "in-state-homes-program",
    "url": {
      "en": "https://indianaenergysaver.com"
    }
  },
  {
    "id": "IN-33",
    "payment_methods": [
      "pos_rebate"
    ],
    "items": [
      "electric_stove"
    ],
    "program": "in_indianaOfficeOfEnergyDevelopment_indianaEnergySaverProgram",
    "amount": {
      "type": "percent",
      "number": 0.5,
      "maximum": 840
    },
    "owner_status": [
      "homeowner",
      "renter"
    ],
    "short_description": {
      "en": "50% of project cost, up to $840 discount for an ENERGY STAR-certified electric stove, cooktop, range, or oven, for moderate income residents.",
      "es": "50% del costo del proyecto, hasta $840 de descuento para una estufa, anafe, cocina o horno eléctrico con certificación ENERGY STAR, para residentes con ingresos moderados."
    },
    "paused": true,
    "low_income": "in-state-hear-program",
    "url": {
      "en": "https://indianaenergysaver.com"
    }
  },
  {
    "id": "IN-34",
    "payment_methods": [
      "pos_rebate"
    ],
    "items": [
      "electric_stove"
    ],
    "program": "in_indianaOfficeOfEnergyDevelopment_indianaEnergySaverProgram",
    "amount": {
      "type": "percent",
      "number": 1,
      "maximum": 840
    },
    "owner_status": [
      "homeowner",
      "renter"
    ],
    "short_description": {
      "en": "100% of project cost, up to $840 discount for an ENERGY STAR-certified electric stove, cooktop, range, or oven, for income-qualified residents.",
      "es": "100% del costo del proyecto, hasta $840 de descuento para una estufa, anafe, cocina o horno eléctrico con certificación ENERGY STAR, para residentes que califiquen según sus ingresos."
    },
    "paused": true,
    "low_income": "in-state-homes-program",
    "url": {
      "en": "https://indianaenergysaver.com"
    }
  },
  {
    "id": "IN-35",
    "payment_methods": [
      "pos_rebate"
    ],
    "items": [
      "electric_panel"
    ],
    "program": "in_indianaOfficeOfEnergyDevelopment_indianaEnergySaverProgram",
    "amount": {
      "type": "percent",
      "number": 0.5,
      "maximum": 4000
    },
    "owner_status": [
      "homeowner"
    ],
    "short_description": {
      "en": "50% of project cost, up to $4,000 discount for an electric panel installed by a qualified contractor, for moderate income residents.",
      "es": "50% del costo del proyecto, hasta $4,000 de descuento para un panel eléctrico instalado por un contratista calificado, para residentes de ingresos moderados."
    },
    "paused": true,
    "low_income": "in-state-hear-program",
    "url": {
      "en": "https://indianaenergysaver.com"
    }
  },
  {
    "id": "IN-36",
    "payment_methods": [
      "pos_rebate"
    ],
    "items": [
      "electric_panel"
    ],
    "program": "in_indianaOfficeOfEnergyDevelopment_indianaEnergySaverProgram",
    "amount": {
      "type": "percent",
      "number": 1,
      "maximum": 4000
    },
    "owner_status": [
      "homeowner",
      "renter"
    ],
    "short_description": {
      "en": "100% of project cost, up to $4,000 discount for an electric panel installed by a qualified contractor, for income-qualified residents.",
      "es": "100% del costo del proyecto, hasta $4,000 de descuento para un panel eléctrico instalado por un contratista calificado, para residentes que califican según sus ingresos."
    },
    "paused": true,
    "low_income": "in-state-homes-program",
    "url": {
      "en": "https://indianaenergysaver.com"
    }
  },
  {
    "id": "IN-37",
    "payment_methods": [
      "pos_rebate"
    ],
    "items": [
      "electric_wiring"
    ],
    "program": "in_indianaOfficeOfEnergyDevelopment_indianaEnergySaverProgram",
    "amount": {
      "type": "percent",
      "number": 0.5,
      "maximum": 2500
    },
    "owner_status": [
      "homeowner"
    ],
    "short_description": {
      "en": "50% of project cost, up to $2,500 discount for electric wiring upgrades installed by a qualified contractor, for moderate income residents.",
      "es": "50% del costo del proyecto, hasta $2,500 de descuento para actualizaciones de cableado eléctrico instaladas por un contratista calificado, para residentes con ingresos moderados."
    },
    "paused": true,
    "low_income": "in-state-hear-program",
    "url": {
      "en": "https://indianaenergysaver.com"
    }
  },
  {
    "id": "IN-38",
    "payment_methods": [
      "pos_rebate"
    ],
    "items": [
      "electric_wiring"
    ],
    "program": "in_indianaOfficeOfEnergyDevelopment_indianaEnergySaverProgram",
    "amount": {
      "type": "percent",
      "number": 1,
      "maximum": 2500
    },
    "owner_status": [
      "homeowner",
      "renter"
    ],
    "short_description": {
      "en": "100% of project cost, up to $2,500 discount for electric wiring installed by a qualified contractor, for income-qualified residents.",
      "es": "100% del costo del proyecto, hasta $2,500 de descuento para cableado eléctrico instalado por un contratista calificado, para residentes que califican según sus ingresos."
    },
    "paused": true,
    "low_income": "in-state-homes-program",
    "url": {
      "en": "https://indianaenergysaver.com"
    }
  },
  {
    "id": "IN-39",
    "payment_methods": [
      "pos_rebate"
    ],
    "items": [
      "air_sealing",
      "attic_or_roof_insulation",
      "duct_sealing",
      "basement_insulation",
      "floor_insulation",
      "wall_insulation"
    ],
    "program": "in_indianaOfficeOfEnergyDevelopment_indianaEnergySaverProgram",
    "amount": {
      "type": "percent",
      "number": 0.5,
      "maximum": 1600
    },
    "owner_status": [
      "homeowner"
    ],
    "short_description": {
      "en": "50% of project cost, up to $1,600 discount for insulation and air sealing installed by a qualified contractor, for moderate income residents.",
      "es": "50% del costo del proyecto, hasta $1,600 de descuento para aislamiento y sellado de aire instalados por un contratista calificado, para residentes de ingresos moderados."
    },
    "paused": true,
    "low_income": "in-state-hear-program",
    "url": {
      "en": "https://indianaenergysaver.com"
    }
  },
  {
    "id": "IN-40",
    "payment_methods": [
      "pos_rebate"
    ],
    "items": [
      "air_sealing",
      "attic_or_roof_insulation",
      "duct_sealing",
      "basement_insulation",
      "floor_insulation",
      "wall_insulation"
    ],
    "program": "in_indianaOfficeOfEnergyDevelopment_indianaEnergySaverProgram",
    "amount": {
      "type": "percent",
      "number": 1,
      "maximum": 1600
    },
    "owner_status": [
      "homeowner"
    ],
    "short_description": {
      "en": "100% of project cost, up to $1,600 discount for insulation and air sealing installed by a qualified contractor, for income qualified residents.",
      "es": "100% del costo del proyecto, hasta $1,600 de descuento para aislamiento y sellado de aire instalados por un contratista calificado, para residentes que califican en cuanto a ingresos."
    },
    "paused": true,
    "low_income": "in-state-homes-program",
    "url": {
      "en": "https://indianaenergysaver.com"
    }
  }
]
