[
  {
    "id": "WI-18",
    "authority_type": "other",
    "authority": "wi-focus-on-energy",
    "eligible_geo_group": "wi-group-focus-on-energy",
    "payment_methods": [
      "rebate"
    ],
    "items": [
      "attic_or_roof_insulation",
      "air_sealing"
    ],
    "program": "wi_focusOnEnergy_dIYInsulation&AirSealingRebates",
    "amount": {
      "type": "dollar_amount",
      "number": 200
    },
    "owner_status": [
      "homeowner",
      "renter"
    ],
    "short_description": {
      "en": "$200 rebate for DIY attic insulation and air sealing, must meet R42 insulation level."
    },
    "start_date": "2024-01-01",
    "end_date": "2024-12-31"
  },
  {
    "id": "WI-19",
    "authority_type": "other",
    "authority": "wi-focus-on-energy",
    "eligible_geo_group": "wi-group-focus-on-energy",
    "payment_methods": [
      "pos_rebate"
    ],
    "items": [
      "heat_pump_water_heater"
    ],
    "program": "wi_focusOnEnergy_waterHeatingRebates",
    "amount": {
      "type": "dollar_amount",
      "number": 300
    },
    "owner_status": [
      "homeowner",
      "renter"
    ],
    "short_description": {
      "en": "Instant discounts starting at $300 for ENERGY STAR® certified electric heat pump water heaters."
    }
  },
  {
    "id": "WI-20",
    "authority_type": "other",
    "authority": "wi-focus-on-energy",
    "eligible_geo_group": "wi-group-focus-on-energy",
    "payment_methods": [
      "pos_rebate"
    ],
    "items": [
      "rooftop_solar_installation"
    ],
    "program": "wi_focusOnEnergy_solarForHomes",
    "amount": {
      "type": "dollar_amount",
      "number": 500,
      "minimum": 500,
      "maximum": 1000
    },
    "owner_status": [
      "homeowner",
      "renter"
    ],
    "short_description": {
      "en": "Up to $500 rebate for residential solar PV systems, additional $500 for rural areas."
    },
    "start_date": "2024-01-01",
    "end_date": "2024-12-31",
    "bonus_available": true
  },
  {
    "id": "WI-21",
    "authority_type": "other",
    "authority": "wi-focus-on-energy",
    "eligible_geo_group": "wi-group-focus-on-energy",
    "payment_methods": [
      "rebate"
    ],
    "items": [
      "smart_thermostat"
    ],
    "program": "wi_focusOnEnergy_smartThermostatsRebates",
    "amount": {
      "type": "dollar_amount",
      "number": 50
    },
    "owner_status": [
      "homeowner",
      "renter"
    ],
    "short_description": {
      "en": "$50 rebate for qualified smart thermostats. Available as instant discounts in the online marketplace or as rebates."
    },
    "start_date": "2024-01-01",
    "bonus_available": true
  },
  {
    "id": "WI-22",
    "authority_type": "other",
    "authority": "wi-focus-on-energy",
    "eligible_geo_group": "wi-group-focus-on-energy",
    "payment_methods": [
      "rebate"
    ],
    "items": [
      "ducted_heat_pump",
      "ductless_heat_pump"
    ],
    "program": "wi_focusOnEnergy_heating&CoolingRebates",
    "amount": {
      "type": "dollar_amount",
      "number": 1000
    },
    "owner_status": [
      "homeowner",
      "renter"
    ],
    "short_description": {
      "en": "$1,000 rebate for air source heat pumps replacing natural gas or electric resistance."
    },
    "start_date": "2024-01-01",
    "end_date": "2024-05-31"
  },
  {
    "id": "WI-23",
    "authority_type": "other",
    "authority": "wi-focus-on-energy",
    "eligible_geo_group": "wi-group-focus-on-energy",
    "payment_methods": [
      "rebate"
    ],
    "items": [
      "ducted_heat_pump",
      "ductless_heat_pump"
    ],
    "program": "wi_focusOnEnergy_heating&CoolingRebates",
    "amount": {
      "type": "dollar_amount",
      "number": 400
    },
    "owner_status": [
      "homeowner",
      "renter"
    ],
    "short_description": {
      "en": "$400 rebate for air source heat pumps replacing propane, oil, existing heat pump, etc."
    },
    "start_date": "2024-01-01",
    "end_date": "2024-05-31"
  },
  {
    "id": "WI-24",
    "authority_type": "other",
    "authority": "wi-focus-on-energy",
    "eligible_geo_group": "wi-group-focus-on-energy",
    "payment_methods": [
      "rebate"
    ],
    "items": [
      "geothermal_heating_installation"
    ],
    "program": "wi_focusOnEnergy_heating&CoolingRebates",
    "amount": {
      "type": "dollar_amount",
      "number": 1000,
      "minimum": 750,
      "maximum": 1000
    },
    "owner_status": [
      "homeowner",
      "renter"
    ],
    "short_description": {
      "en": "$750 rebate for certified geothermal heat pumps without natural gas service or $1000 with natural gas service."
    },
    "start_date": "2024-01-01",
    "end_date": "2024-05-31"
  },
  {
    "id": "WI-25",
    "authority_type": "other",
    "authority": "wi-focus-on-energy",
    "eligible_geo_group": "wi-group-focus-on-energy",
    "payment_methods": [
      "rebate"
    ],
    "items": [
      "air_sealing"
    ],
    "program": "wi_focusOnEnergy_insulation&AirSealingRebates",
    "amount": {
      "type": "dollar_amount",
      "number": 675
    },
    "owner_status": [
      "homeowner",
      "renter"
    ],
    "short_description": {
      "en": "Up to $675 rebate for ENERGY STAR® Qualified Air Sealing, assessment required."
    },
    "start_date": "2024-01-01",
    "end_date": "2024-05-31"
  },
  {
    "id": "WI-26",
    "authority_type": "other",
    "authority": "wi-focus-on-energy",
    "eligible_geo_group": "wi-group-focus-on-energy",
    "payment_methods": [
      "pos_rebate"
    ],
    "items": [
      "air_sealing"
    ],
    "program": "wi_focusOnEnergy_insulation&AirSealingRebates",
    "amount": {
      "type": "dollar_amount",
      "number": 1125
    },
    "owner_status": [
      "homeowner",
      "renter"
    ],
    "short_description": {
      "en": "Up to $1,125 rebate for ENERGY STAR® Qualified Air Sealing, assessment required. For income-qualified customers."
    },
    "start_date": "2024-01-01",
    "end_date": "2024-05-31",
    "low_income": "wi-focus-on-energy"
  },
  {
    "id": "WI-27",
    "authority_type": "other",
    "authority": "wi-focus-on-energy",
    "eligible_geo_group": "wi-group-focus-on-energy",
    "payment_methods": [
      "rebate"
    ],
    "items": [
      "attic_or_roof_insulation"
    ],
    "program": "wi_focusOnEnergy_insulation&AirSealingRebates",
    "amount": {
      "type": "dollar_amount",
      "number": 525
    },
    "owner_status": [
      "homeowner",
      "renter"
    ],
    "short_description": {
      "en": "Up to $525 rebate for attic insulation."
    },
    "start_date": "2024-01-01",
    "end_date": "2024-05-31",
    "bonus_available": true
  },
  {
    "id": "WI-28",
    "authority_type": "other",
    "authority": "wi-focus-on-energy",
    "eligible_geo_group": "wi-group-focus-on-energy",
    "payment_methods": [
      "pos_rebate"
    ],
    "items": [
      "attic_or_roof_insulation"
    ],
    "program": "wi_focusOnEnergy_insulation&AirSealingRebates",
    "amount": {
      "type": "dollar_amount",
      "number": 675
    },
    "owner_status": [
      "homeowner",
      "renter"
    ],
    "short_description": {
      "en": "Up to $675 rebate for attic insulation. For income-qualified customers."
    },
    "start_date": "2024-01-01",
    "end_date": "2024-05-31",
    "bonus_available": true,
    "low_income": "wi-focus-on-energy"
  },
  {
    "id": "WI-29",
    "authority_type": "other",
    "authority": "wi-focus-on-energy",
    "eligible_geo_group": "wi-group-focus-on-energy",
    "payment_methods": [
      "rebate"
    ],
    "items": [
      "other_insulation"
    ],
    "program": "wi_focusOnEnergy_insulation&AirSealingRebates",
    "amount": {
      "type": "dollar_amount",
      "number": 150
    },
    "owner_status": [
      "homeowner",
      "renter"
    ],
    "short_description": {
      "en": "Up to $150 rebate for foundation insulation."
    },
    "start_date": "2024-01-01",
    "end_date": "2024-05-31",
    "bonus_available": true
  },
  {
    "id": "WI-30",
    "authority_type": "other",
    "authority": "wi-focus-on-energy",
    "eligible_geo_group": "wi-group-focus-on-energy",
    "payment_methods": [
      "pos_rebate"
    ],
    "items": [
      "other_insulation"
    ],
    "program": "wi_focusOnEnergy_insulation&AirSealingRebates",
    "amount": {
      "type": "dollar_amount",
      "number": 225
    },
    "owner_status": [
      "homeowner",
      "renter"
    ],
    "short_description": {
      "en": "Up to $225 rebate for foundation insulation. For income-qualified customers."
    },
    "start_date": "2024-01-01",
    "end_date": "2024-05-31",
    "bonus_available": true,
    "low_income": "wi-focus-on-energy"
  },
  {
    "id": "WI-31",
    "authority_type": "other",
    "authority": "wi-focus-on-energy",
    "eligible_geo_group": "wi-group-focus-on-energy",
    "payment_methods": [
      "rebate"
    ],
    "items": [
      "wall_insulation"
    ],
    "program": "wi_focusOnEnergy_insulation&AirSealingRebates",
    "amount": {
      "type": "dollar_amount",
      "number": 450
    },
    "owner_status": [
      "homeowner",
      "renter"
    ],
    "short_description": {
      "en": "Up to $450 rebate for wall insulation."
    },
    "start_date": "2024-01-01",
    "end_date": "2024-05-31",
    "bonus_available": true
  },
  {
    "id": "WI-32",
    "authority_type": "other",
    "authority": "wi-focus-on-energy",
    "eligible_geo_group": "wi-group-focus-on-energy",
    "payment_methods": [
      "rebate"
    ],
    "items": [
      "duct_sealing"
    ],
    "program": "wi_focusOnEnergy_insulation&AirSealingRebates",
    "amount": {
      "type": "dollar_amount",
      "number": 75
    },
    "owner_status": [
      "homeowner",
      "renter"
    ],
    "short_description": {
      "en": "Up to $75 rebate for duct sealing & insulation."
    },
    "start_date": "2024-01-01",
    "end_date": "2024-05-31",
    "bonus_available": true
  },
  {
    "id": "WI-34",
    "authority_type": "utility",
    "authority": "wi-barron-electric-cooperative",
    "payment_methods": [
      "pos_rebate"
    ],
    "items": [
      "electric_vehicle_charger"
    ],
    "program": "wi_barronElectricCooperative_energySavingsRebates:EVChargers",
    "amount": {
      "type": "percent",
      "number": 1
    },
    "owner_status": [
      "homeowner"
    ],
    "short_description": {
      "en": "Free smart EV charger ($1,100 value) for members who purchase an EV and meet requirements."
    },
    "end_date": "2024-12-13"
  },
  {
    "id": "WI-35",
    "authority_type": "utility",
    "authority": "wi-barron-electric-cooperative",
    "payment_methods": [
      "rebate"
    ],
    "items": [
      "electric_vehicle_charger"
    ],
    "program": "wi_barronElectricCooperative_energySavingsRebates:EVChargers",
    "amount": {
      "type": "dollar_amount",
      "number": 400
    },
    "owner_status": [
      "homeowner"
    ],
    "short_description": {
      "en": "$400 rebate for alternative EV chargers compatible with load management equipment."
    },
    "end_date": "2024-12-13"
  },
  {
    "id": "WI-36",
    "authority_type": "utility",
    "authority": "wi-barron-electric-cooperative",
    "payment_methods": [
      "rebate"
    ],
    "items": [
      "geothermal_heating_installation"
    ],
    "program": "wi_barronElectricCooperative_energySavingsRebates:HVAC",
    "amount": {
      "type": "percent",
      "number": 0.2
    },
    "owner_status": [
      "homeowner"
    ],
    "short_description": {
      "en": "20% rebate for geothermal heat pumps, up to $500/ton."
    },
    "start_date": "2024-01-01",
    "end_date": "2024-12-13"
  },
  {
    "id": "WI-37",
    "authority_type": "utility",
    "authority": "wi-barron-electric-cooperative",
    "payment_methods": [
      "account_credit",
      "rebate"
    ],
    "items": [
      "non_heat_pump_water_heater"
    ],
    "program": "wi_barronElectricCooperative_energySavingsRebates:WaterHeaters",
    "amount": {
      "type": "percent",
      "number": 0.2,
      "maximum": 300
    },
    "owner_status": [
      "homeowner"
    ],
    "short_description": {
      "en": "20% rebate for residential electric water heaters, up to $150 for 75-99 gallons and up to $300 for 100+ gallons. Must be load managed."
    },
    "start_date": "2024-01-01",
    "end_date": "2024-12-13"
  },
  {
    "id": "WI-38",
    "authority_type": "utility",
    "authority": "wi-barron-electric-cooperative",
    "payment_methods": [
      "account_credit",
      "rebate"
    ],
    "items": [
      "heat_pump_water_heater"
    ],
    "program": "wi_barronElectricCooperative_energySavingsRebates:WaterHeaters",
    "amount": {
      "type": "percent",
      "number": 0.2,
      "maximum": 300
    },
    "owner_status": [
      "homeowner"
    ],
    "short_description": {
      "en": "20% rebate for heat pump water heaters with EF 2.00+, up to $300."
    },
    "start_date": "2024-01-01",
    "end_date": "2024-12-13"
  },
  {
    "id": "WI-39",
    "authority_type": "utility",
    "authority": "wi-barron-electric-cooperative",
    "payment_methods": [
      "account_credit",
      "rebate"
    ],
    "items": [
      "ducted_heat_pump",
      "ductless_heat_pump"
    ],
    "program": "wi_barronElectricCooperative_energySavingsRebates:HVAC",
    "amount": {
      "type": "percent",
      "number": 0.2
    },
    "owner_status": [
      "homeowner"
    ],
    "short_description": {
      "en": "20% rebate for air source & mini-split heat pumps, up to $300/ton. SEER2 14.3+, HSPF2 7.5+."
    },
    "start_date": "2024-01-01",
    "end_date": "2024-12-13"
  },
  {
    "id": "WI-40",
    "authority_type": "utility",
    "authority": "wi-barron-electric-cooperative",
    "payment_methods": [
      "account_credit"
    ],
    "items": [
      "electric_stove"
    ],
    "program": "wi_barronElectricCooperative_energySavingsRebates:EnergyStarAppliances",
    "amount": {
      "type": "dollar_amount",
      "number": 25
    },
    "owner_status": [
      "homeowner"
    ],
    "short_description": {
      "en": "$25 rebate for ENERGY STAR® induction ranges."
    },
    "start_date": "2024-01-01",
    "end_date": "2024-12-13"
  },
  {
    "id": "WI-41",
    "authority_type": "utility",
    "authority": "wi-barron-electric-cooperative",
    "payment_methods": [
      "account_credit"
    ],
    "items": [
      "heat_pump_clothes_dryer"
    ],
    "program": "wi_barronElectricCooperative_energySavingsRebates:EnergyStarAppliances",
    "amount": {
      "type": "dollar_amount",
      "number": 25
    },
    "owner_status": [
      "homeowner"
    ],
    "short_description": {
      "en": "$25 rebate for ENERGY STAR® clothes dryers."
    },
    "start_date": "2024-01-01",
    "end_date": "2024-12-13"
  },
  {
    "id": "WI-42",
    "authority_type": "utility",
    "authority": "wi-barron-electric-cooperative",
    "payment_methods": [
      "account_credit",
      "rebate"
    ],
    "items": [
      "other_weatherization"
    ],
    "program": "wi_barronElectricCooperative_energySavingsRebates:AuditRecommendedImprovements",
    "amount": {
      "type": "percent",
      "number": 0.2,
      "maximum": 500
    },
    "owner_status": [
      "homeowner"
    ],
    "short_description": {
      "en": "20% of cost for energy efficiency improvements, up to $500."
    },
    "end_date": "2024-12-13"
  },
  {
    "id": "WI-43",
    "authority_type": "utility",
    "authority": "wi-bayfield-electric-cooperative",
    "payment_methods": [
      "rebate"
    ],
    "items": [
      "electric_vehicle_charger"
    ],
    "program": "wi_bayfieldElectricCooperative_eVChargerRebates",
    "amount": {
      "type": "dollar_amount",
      "number": 400
    },
    "owner_status": [
      "homeowner"
    ],
    "short_description": {
      "en": "Up to $400 incentive for EV chargers."
    },
    "end_date": "2024-12-31"
  },
  {
    "id": "WI-44",
    "authority_type": "utility",
    "authority": "wi-bayfield-electric-cooperative",
    "payment_methods": [
      "rebate"
    ],
    "items": [
      "electric_vehicle_charger"
    ],
    "program": "wi_bayfieldElectricCooperative_eVChargerRebates",
    "amount": {
      "type": "dollar_amount",
      "number": 800
    },
    "owner_status": [
      "homeowner"
    ],
    "short_description": {
      "en": "Up to $800 incentive for smart EV chargers with integrated metering."
    },
    "end_date": "2024-12-31"
  },
  {
    "id": "WI-45",
    "authority_type": "utility",
    "authority": "wi-bayfield-electric-cooperative",
    "payment_methods": [
      "rebate"
    ],
    "items": [
      "geothermal_heating_installation"
    ],
    "program": "wi_bayfieldElectricCooperative_hVACRebates",
    "amount": {
      "type": "dollars_per_unit",
      "number": 500,
      "unit": "ton"
    },
    "owner_status": [
      "homeowner"
    ],
    "short_description": {
      "en": "$500/ton for geothermal heat pumps."
    },
    "end_date": "2024-12-31"
  },
  {
    "id": "WI-46",
    "authority_type": "utility",
    "authority": "wi-bayfield-electric-cooperative",
    "payment_methods": [
      "rebate"
    ],
    "items": [
      "heat_pump_clothes_dryer"
    ],
    "program": "wi_bayfieldElectricCooperative_applianceRebates",
    "amount": {
      "type": "dollar_amount",
      "number": 50
    },
    "owner_status": [
      "homeowner"
    ],
    "short_description": {
      "en": "$50 for ENERGY STAR® clothes dryers."
    },
    "end_date": "2024-12-31"
  },
  {
    "id": "WI-47",
    "authority_type": "utility",
    "authority": "wi-bayfield-electric-cooperative",
    "payment_methods": [
      "rebate"
    ],
    "items": [
      "non_heat_pump_water_heater"
    ],
    "program": "wi_bayfieldElectricCooperative_waterHeaterRebates",
    "amount": {
      "type": "dollar_amount",
      "number": 300,
      "minimum": 150,
      "maximum": 300
    },
    "owner_status": [
      "homeowner"
    ],
    "short_description": {
      "en": "$150 rebate for 75-99 gallon residential high efficiency water heaters or $300 for 100+ gallons. UEF must be at least .88."
    },
    "end_date": "2024-12-31"
  },
  {
    "id": "WI-48",
    "authority_type": "utility",
    "authority": "wi-bayfield-electric-cooperative",
    "payment_methods": [
      "rebate"
    ],
    "items": [
      "heat_pump_water_heater"
    ],
    "program": "wi_bayfieldElectricCooperative_waterHeaterRebates",
    "amount": {
      "type": "dollar_amount",
      "number": 300
    },
    "owner_status": [
      "homeowner"
    ],
    "short_description": {
      "en": "$300 rebate for heat pump water heaters, UEF .88, on load control."
    },
    "end_date": "2024-12-31"
  },
  {
    "id": "WI-49",
    "authority_type": "utility",
    "authority": "wi-bayfield-electric-cooperative",
    "payment_methods": [
      "rebate"
    ],
    "items": [
      "ducted_heat_pump",
      "ductless_heat_pump"
    ],
    "program": "wi_bayfieldElectricCooperative_hVACRebates",
    "amount": {
      "type": "dollars_per_unit",
      "number": 300,
      "unit": "ton"
    },
    "owner_status": [
      "homeowner"
    ],
    "short_description": {
      "en": "$300/ton for SEER2 14.3+, HSPF2 7.5+ or SEER 15+, HSPF 8.8+ air source & mini-split heat pumps."
    },
    "end_date": "2024-12-31"
  },
  {
    "id": "WI-50",
    "authority_type": "utility",
    "authority": "wi-bayfield-electric-cooperative",
    "payment_methods": [
      "rebate"
    ],
    "items": [
      "electric_stove"
    ],
    "program": "wi_bayfieldElectricCooperative_applianceRebates",
    "amount": {
      "type": "dollar_amount",
      "number": 50
    },
    "owner_status": [
      "homeowner"
    ],
    "short_description": {
      "en": "$50 for induction ranges."
    },
    "end_date": "2024-12-31"
  },
  {
    "id": "WI-51",
    "authority_type": "utility",
    "authority": "wi-bayfield-electric-cooperative",
    "payment_methods": [
      "rebate"
    ],
    "items": [
      "smart_thermostat"
    ],
    "program": "wi_bayfieldElectricCooperative_hVACRebates",
    "amount": {
      "type": "dollar_amount",
      "number": 50
    },
    "owner_status": [
      "homeowner"
    ],
    "short_description": {
      "en": "$25 incentive for Honeywell or Emerson brand smart thermostats enrolled in Load Management Program."
    },
    "end_date": "2024-12-31"
  },
  {
    "id": "WI-52",
    "authority_type": "utility",
    "authority": "wi-bayfield-electric-cooperative",
    "payment_methods": [
      "rebate"
    ],
    "items": [
      "other_weatherization"
    ],
    "program": "wi_bayfieldElectricCooperative_auditRecommendedImprovementRebates",
    "amount": {
      "type": "dollar_amount",
      "number": 500
    },
    "owner_status": [
      "homeowner"
    ],
    "short_description": {
      "en": "Up to $500 for audit-recommended energy efficiency improvements."
    },
    "end_date": "2024-12-31"
  },
  {
    "id": "WI-53",
    "authority_type": "utility",
    "authority": "wi-chippewa-valley-electric-cooperative",
    "payment_methods": [
      "rebate"
    ],
    "items": [
      "electric_vehicle_charger"
    ],
    "program": "wi_chippewaValleyElectricCooperative_electricVehicleChargingStationIncentives",
    "amount": {
      "type": "dollar_amount",
      "number": 400
    },
    "owner_status": [
      "homeowner"
    ],
    "short_description": {
      "en": "$400 incentive towards the purchase of any EV charger."
    },
    "end_date": "2023-12-31"
  },
  {
    "id": "WI-54",
    "authority_type": "utility",
    "authority": "wi-chippewa-valley-electric-cooperative",
    "payment_methods": [
      "account_credit"
    ],
    "items": [
      "geothermal_heating_installation"
    ],
    "program": "wi_chippewaValleyElectricCooperative_hVACIncentives",
    "amount": {
      "type": "dollars_per_unit",
      "number": 800,
      "unit": "ton"
    },
    "owner_status": [
      "homeowner"
    ],
    "short_description": {
      "en": "Up to $800/ton rebate for geothermal heat pumps."
    },
    "end_date": "2024-12-31"
  },
  {
    "id": "WI-55",
    "authority_type": "utility",
    "authority": "wi-chippewa-valley-electric-cooperative",
    "payment_methods": [
      "account_credit"
    ],
    "items": [
      "heat_pump_clothes_dryer"
    ],
    "program": "wi_chippewaValleyElectricCooperative_applianceIncentives",
    "amount": {
      "type": "dollar_amount",
      "number": 25
    },
    "owner_status": [
      "homeowner"
    ],
    "short_description": {
      "en": "$25 rebate for ENERGY STAR® clothes dryers."
    },
    "end_date": "2024-12-31"
  },
  {
    "id": "WI-56",
    "authority_type": "utility",
    "authority": "wi-chippewa-valley-electric-cooperative",
    "payment_methods": [
      "account_credit"
    ],
    "items": [
      "non_heat_pump_water_heater"
    ],
    "program": "wi_chippewaValleyElectricCooperative_waterHeaterIncentives",
    "amount": {
      "type": "dollar_amount",
      "number": 461,
      "minimum": 63,
      "maximum": 461
    },
    "owner_status": [
      "homeowner"
    ],
    "short_description": {
      "en": "Up to $461/unit rebate for high efficiency water heaters. UEF must be .88 or greater, must be controlled by load control program."
    },
    "start_date": "2024-01-01",
    "end_date": "2024-12-31"
  },
  {
    "id": "WI-57",
    "authority_type": "utility",
    "authority": "wi-chippewa-valley-electric-cooperative",
    "payment_methods": [
      "account_credit"
    ],
    "items": [
      "heat_pump_water_heater"
    ],
    "program": "wi_chippewaValleyElectricCooperative_waterHeaterIncentives",
    "amount": {
      "type": "dollar_amount",
      "number": 300
    },
    "owner_status": [
      "homeowner"
    ],
    "short_description": {
      "en": "Up to $300/unit rebate for heat pump water heaters. UEF must be 2.00 or greater."
    },
    "start_date": "2024-01-01",
    "end_date": "2024-12-31"
  },
  {
    "id": "WI-58",
    "authority_type": "utility",
    "authority": "wi-chippewa-valley-electric-cooperative",
    "payment_methods": [
      "account_credit"
    ],
    "items": [
      "ducted_heat_pump",
      "ductless_heat_pump"
    ],
    "program": "wi_chippewaValleyElectricCooperative_hVACIncentives",
    "amount": {
      "type": "dollars_per_unit",
      "number": 300,
      "unit": "ton"
    },
    "owner_status": [
      "homeowner"
    ],
    "short_description": {
      "en": "Up to $300/ton rebate for air source & mini-split heat pumps. SEER2 14.3+, HSPF2 7.5+ or SEER 15+, HSPF 8.8+."
    },
    "end_date": "2024-12-31"
  },
  {
    "id": "WI-59",
    "authority_type": "utility",
    "authority": "wi-chippewa-valley-electric-cooperative",
    "payment_methods": [
      "account_credit"
    ],
    "items": [
      "electric_stove"
    ],
    "program": "wi_chippewaValleyElectricCooperative_applianceIncentives",
    "amount": {
      "type": "dollar_amount",
      "number": 25
    },
    "owner_status": [
      "homeowner"
    ],
    "short_description": {
      "en": "$25 incentive for induction ranges."
    },
    "end_date": "2024-12-31"
  },
  {
    "id": "WI-60",
    "authority_type": "utility",
    "authority": "wi-chippewa-valley-electric-cooperative",
    "payment_methods": [
      "account_credit"
    ],
    "items": [
      "smart_thermostat"
    ],
    "program": "wi_chippewaValleyElectricCooperative_hVACIncentives",
    "amount": {
      "type": "dollar_amount",
      "number": 25
    },
    "owner_status": [
      "homeowner"
    ],
    "short_description": {
      "en": "$25 incentive for Honeywell or Emerson brand smart thermostats enrolled in Load Management Program."
    },
    "end_date": "2024-12-31"
  },
  {
    "id": "WI-61",
    "authority_type": "utility",
    "authority": "wi-chippewa-valley-electric-cooperative",
    "payment_methods": [
      "rebate"
    ],
    "items": [
      "other_weatherization"
    ],
    "program": "wi_chippewaValleyElectricCooperative_auditRecommendedImprovementsIncentives",
    "amount": {
      "type": "dollar_amount",
      "number": 500
    },
    "owner_status": [
      "homeowner"
    ],
    "short_description": {
      "en": "Up to $500 for audit-recommended energy efficiency improvements."
    },
    "end_date": "2024-12-31"
  },
  {
    "id": "WI-62",
    "authority_type": "utility",
    "authority": "wi-clark-electric-cooperative",
    "payment_methods": [
      "rebate"
    ],
    "items": [
      "heat_pump_clothes_dryer"
    ],
    "program": "wi_clarkElectricCooperative_eNERGYSTARApplianceIncentives",
    "amount": {
      "type": "dollar_amount",
      "number": 25
    },
    "owner_status": [
      "homeowner"
    ],
    "short_description": {
      "en": "$25 rebate for ENERGY STAR® clothes dryers."
    },
    "end_date": "2024-12-31"
  },
  {
    "id": "WI-63",
    "authority_type": "utility",
    "authority": "wi-clark-electric-cooperative",
    "payment_methods": [
      "rebate"
    ],
    "items": [
      "non_heat_pump_water_heater"
    ],
    "program": "wi_clarkElectricCooperative_waterHeaterIncentives",
    "amount": {
      "type": "dollar_amount",
      "number": 500,
      "minimum": 50,
      "maximum": 500
    },
    "owner_status": [
      "homeowner"
    ],
    "short_description": {
      "en": "Up to $500 rebate for an electric water heaters, depending on efficiency and capacity. Must be on load control."
    },
    "end_date": "2024-12-31"
  },
  {
    "id": "WI-64",
    "authority_type": "utility",
    "authority": "wi-clark-electric-cooperative",
    "payment_methods": [
      "rebate"
    ],
    "items": [
      "heat_pump_water_heater"
    ],
    "program": "wi_clarkElectricCooperative_waterHeaterIncentives",
    "amount": {
      "type": "dollar_amount",
      "number": 400
    },
    "owner_status": [
      "homeowner"
    ],
    "short_description": {
      "en": "$400 rebate for heat pump water heaters, UEF .88, on load control."
    },
    "end_date": "2024-12-31"
  },
  {
    "id": "WI-65",
    "authority_type": "utility",
    "authority": "wi-clark-electric-cooperative",
    "payment_methods": [
      "rebate"
    ],
    "items": [
      "electric_stove"
    ],
    "program": "wi_clarkElectricCooperative_eNERGYSTARApplianceIncentives",
    "amount": {
      "type": "dollar_amount",
      "number": 25
    },
    "owner_status": [
      "homeowner"
    ],
    "short_description": {
      "en": "$25 rebate for induction ranges."
    },
    "end_date": "2024-12-31"
  },
  {
    "id": "WI-66",
    "authority_type": "utility",
    "authority": "wi-clark-electric-cooperative",
    "payment_methods": [
      "rebate"
    ],
    "items": [
      "ducted_heat_pump",
      "ductless_heat_pump"
    ],
    "program": "wi_clarkElectricCooperative_hVACIncentives",
    "amount": {
      "type": "dollars_per_unit",
      "number": 400,
      "unit": "ton"
    },
    "owner_status": [
      "homeowner"
    ],
    "short_description": {
      "en": "Up to $400/ton rebate for air source & mini-split heat pumps. SEER2 14.3+, HSPF2 7.5+ or SEER 15+, HSPF 8.8+."
    },
    "end_date": "2024-12-31"
  },
  {
    "id": "WI-67",
    "authority_type": "utility",
    "authority": "wi-clark-electric-cooperative",
    "payment_methods": [
      "rebate"
    ],
    "items": [
      "geothermal_heating_installation"
    ],
    "program": "wi_clarkElectricCooperative_hVACIncentives",
    "amount": {
      "type": "dollars_per_unit",
      "number": 850,
      "unit": "ton"
    },
    "owner_status": [
      "homeowner"
    ],
    "short_description": {
      "en": "Up to $850/ton rebate for geothermal heat pumps."
    },
    "end_date": "2024-12-31"
  },
  {
    "id": "WI-68",
    "authority_type": "utility",
    "authority": "wi-clark-electric-cooperative",
    "payment_methods": [
      "rebate"
    ],
    "items": [
      "smart_thermostat"
    ],
    "program": "wi_clarkElectricCooperative_hVACIncentives",
    "amount": {
      "type": "dollar_amount",
      "number": 25
    },
    "owner_status": [
      "homeowner"
    ],
    "short_description": {
      "en": "$25 incentive for Honeywell or Emerson brand smart thermostats enrolled in Load Management Program."
    },
    "end_date": "2024-12-31"
  },
  {
    "id": "WI-69",
    "authority_type": "utility",
    "authority": "wi-clark-electric-cooperative",
    "payment_methods": [
      "rebate"
    ],
    "items": [
      "other_weatherization"
    ],
    "program": "wi_clarkElectricCooperative_auditRecommendedImprovementsIncentives",
    "amount": {
      "type": "dollar_amount",
      "number": 500
    },
    "owner_status": [
      "homeowner"
    ],
    "short_description": {
      "en": "Up to $500 for audit-recommended energy efficiency improvements."
    },
    "end_date": "2024-12-31"
  },
  {
    "id": "WI-70",
    "authority_type": "utility",
    "authority": "wi-dunn-energy-cooperative",
    "payment_methods": [
      "account_credit"
    ],
    "items": [
      "heat_pump_clothes_dryer"
    ],
    "program": "wi_dunnEnergyCooperative_homeRebates",
    "amount": {
      "type": "dollar_amount",
      "number": 25
    },
    "owner_status": [
      "homeowner"
    ],
    "short_description": {
      "en": "$25 rebate for ENERGY STAR® rated clothes dryers."
    },
    "start_date": "2024-01-01",
    "end_date": "2024-12-31"
  },
  {
    "id": "WI-71",
    "authority_type": "utility",
    "authority": "wi-dunn-energy-cooperative",
    "payment_methods": [
      "account_credit"
    ],
    "items": [
      "electric_stove"
    ],
    "program": "wi_dunnEnergyCooperative_homeRebates",
    "amount": {
      "type": "dollar_amount",
      "number": 25
    },
    "owner_status": [
      "homeowner"
    ],
    "short_description": {
      "en": "$25 rebate for ENERGY STAR® rated induction ranges."
    },
    "start_date": "2024-01-01",
    "end_date": "2024-12-31"
  },
  {
    "id": "WI-72",
    "authority_type": "utility",
    "authority": "wi-dunn-energy-cooperative",
    "payment_methods": [
      "rebate"
    ],
    "items": [
      "electric_vehicle_charger"
    ],
    "program": "wi_dunnEnergyCooperative_electricVehicleIncentives",
    "amount": {
      "type": "dollar_amount",
      "number": 400
    },
    "owner_status": [
      "homeowner"
    ],
    "short_description": {
      "en": "$400 incentive for new EV chargers."
    },
    "end_date": "2024-12-31"
  },
  {
    "id": "WI-73",
    "authority_type": "utility",
    "authority": "wi-dunn-energy-cooperative",
    "payment_methods": [
      "rebate"
    ],
    "items": [
      "electric_vehicle_charger"
    ],
    "program": "wi_dunnEnergyCooperative_electricVehicleIncentives",
    "amount": {
      "type": "dollar_amount",
      "number": 800
    },
    "owner_status": [
      "homeowner"
    ],
    "short_description": {
      "en": "$800 incentive for smart EV chargers with integrated metering."
    },
    "end_date": "2024-12-31"
  },
  {
    "id": "WI-74",
    "authority_type": "utility",
    "authority": "wi-dunn-energy-cooperative",
    "payment_methods": [
      "account_credit"
    ],
    "items": [
      "geothermal_heating_installation"
    ],
    "program": "wi_dunnEnergyCooperative_homeRebates",
    "amount": {
      "type": "dollars_per_unit",
      "number": 500,
      "unit": "ton"
    },
    "owner_status": [
      "homeowner"
    ],
    "short_description": {
      "en": "$500/ton rebate for geothermal heat pumps."
    },
    "start_date": "2024-01-01",
    "end_date": "2024-12-31"
  },
  {
    "id": "WI-75",
    "authority_type": "utility",
    "authority": "wi-dunn-energy-cooperative",
    "payment_methods": [
      "account_credit"
    ],
    "items": [
      "heat_pump_clothes_dryer"
    ],
    "program": "wi_dunnEnergyCooperative_homeRebates",
    "amount": {
      "type": "dollar_amount",
      "number": 50
    },
    "owner_status": [
      "homeowner"
    ],
    "short_description": {
      "en": "$50 rebate for heat pump clothes dryers."
    },
    "start_date": "2024-01-01",
    "end_date": "2024-12-31"
  },
  {
    "id": "WI-76",
    "authority_type": "utility",
    "authority": "wi-dunn-energy-cooperative",
    "payment_methods": [
      "account_credit"
    ],
    "items": [
      "non_heat_pump_water_heater"
    ],
    "program": "wi_dunnEnergyCooperative_homeRebates",
    "amount": {
      "type": "dollar_amount",
      "number": 300,
      "minimum": 150,
      "maximum": 300
    },
    "owner_status": [
      "homeowner"
    ],
    "short_description": {
      "en": "Up to $300 rebate for residential high efficiency water heaters. UEF of at least .88. Must be on load control."
    },
    "start_date": "2024-01-01",
    "end_date": "2024-12-31"
  },
  {
    "id": "WI-77",
    "authority_type": "utility",
    "authority": "wi-dunn-energy-cooperative",
    "payment_methods": [
      "account_credit"
    ],
    "items": [
      "heat_pump_water_heater"
    ],
    "program": "wi_dunnEnergyCooperative_homeRebates",
    "amount": {
      "type": "dollar_amount",
      "number": 300
    },
    "owner_status": [
      "homeowner"
    ],
    "short_description": {
      "en": "Up to $300 rebate for heat pump water heaters. Must have UEF of at least 2.20."
    },
    "start_date": "2024-01-01",
    "end_date": "2024-12-31"
  },
  {
    "id": "WI-78",
    "authority_type": "utility",
    "authority": "wi-dunn-energy-cooperative",
    "payment_methods": [
      "account_credit"
    ],
    "items": [
      "ducted_heat_pump",
      "ductless_heat_pump"
    ],
    "program": "wi_dunnEnergyCooperative_homeRebates",
    "amount": {
      "type": "dollars_per_unit",
      "number": 300,
      "unit": "ton"
    },
    "owner_status": [
      "homeowner"
    ],
    "short_description": {
      "en": "$300/ton rebate for air source heat pumps/mini-splits. Must be 14.3+ SEER2 , HSPF2 7.5+ or SEER 15+, HSPF 8.8+."
    },
    "start_date": "2024-01-01",
    "end_date": "2024-12-31"
  },
  {
    "id": "WI-79",
    "authority_type": "utility",
    "authority": "wi-dunn-energy-cooperative",
    "payment_methods": [
      "account_credit"
    ],
    "items": [
      "geothermal_heating_installation"
    ],
    "program": "wi_dunnEnergyCooperative_homeRebates",
    "amount": {
      "type": "dollars_per_unit",
      "number": 500,
      "unit": "ton"
    },
    "owner_status": [
      "homeowner"
    ],
    "short_description": {
      "en": "$500/ton rebate for geothermal heat pumps. AHRI Certificate must be provided."
    },
    "start_date": "2024-01-01",
    "end_date": "2024-12-31"
  },
  {
    "id": "WI-80",
    "authority_type": "utility",
    "authority": "wi-dunn-energy-cooperative",
    "payment_methods": [
      "account_credit"
    ],
    "items": [
      "smart_thermostat"
    ],
    "program": "wi_dunnEnergyCooperative_homeRebates",
    "amount": {
      "type": "dollar_amount",
      "number": 25
    },
    "owner_status": [
      "homeowner"
    ],
    "short_description": {
      "en": "$25 rebate for Emerson or Honeywell smart thermostats."
    },
    "start_date": "2024-01-01",
    "end_date": "2024-12-31"
  },
  {
    "id": "WI-81",
    "authority_type": "utility",
    "authority": "wi-east-central-energy",
    "payment_methods": [
      "rebate"
    ],
    "items": [
      "electric_vehicle_charger"
    ],
    "program": "wi_eastCentralEnergy_residentialRebates",
    "amount": {
      "type": "dollar_amount",
      "number": 500
    },
    "owner_status": [
      "homeowner"
    ],
    "short_description": {
      "en": "$500 rebate for metered level 2 EV chargers."
    }
  },
  {
    "id": "WI-82",
    "authority_type": "utility",
    "authority": "wi-east-central-energy",
    "payment_methods": [
      "rebate"
    ],
    "items": [
      "geothermal_heating_installation"
    ],
    "program": "wi_eastCentralEnergy_residentialRebates",
    "amount": {
      "type": "dollars_per_unit",
      "number": 400,
      "unit": "ton"
    },
    "owner_status": [
      "homeowner"
    ],
    "short_description": {
      "en": "$400/ton rebate for ENERGY STAR® rated ground source heat pumps."
    }
  },
  {
    "id": "WI-83",
    "authority_type": "utility",
    "authority": "wi-east-central-energy",
    "payment_methods": [
      "rebate"
    ],
    "items": [
      "heat_pump_water_heater"
    ],
    "program": "wi_eastCentralEnergy_residentialRebates",
    "amount": {
      "type": "dollar_amount",
      "number": 500
    },
    "owner_status": [
      "homeowner"
    ],
    "short_description": {
      "en": "$500 rebate for ENERGY STAR® rated heat pump water heaters."
    }
  },
  {
    "id": "WI-84",
    "authority_type": "utility",
    "authority": "wi-east-central-energy",
    "payment_methods": [
      "rebate"
    ],
    "items": [
      "ducted_heat_pump",
      "ductless_heat_pump"
    ],
    "program": "wi_eastCentralEnergy_residentialRebates",
    "amount": {
      "type": "dollar_amount",
      "number": 1000
    },
    "owner_status": [
      "homeowner"
    ],
    "short_description": {
      "en": "Up to $1,000 rebate for air source heat pumps, must meet SEER2 and HSPF2."
    }
  },
  {
    "id": "WI-85",
    "authority_type": "utility",
    "authority": "wi-east-central-energy",
    "payment_methods": [
      "rebate"
    ],
    "items": [
      "heat_pump_clothes_dryer"
    ],
    "program": "wi_eastCentralEnergy_residentialRebates",
    "amount": {
      "type": "dollar_amount",
      "number": 25
    },
    "owner_status": [
      "homeowner"
    ],
    "short_description": {
      "en": "$25 rebate for ENERGY STAR® rated electric clothes dryers."
    }
  },
  {
    "id": "WI-86",
    "authority_type": "utility",
    "authority": "wi-east-central-energy",
    "payment_methods": [
      "rebate"
    ],
    "items": [
      "other"
    ],
    "program": "wi_eastCentralEnergy_residentialRebates",
    "amount": {
      "type": "dollar_amount",
      "number": 400
    },
    "owner_status": [
      "homeowner"
    ],
    "short_description": {
      "en": "$400 rebate for pool air source heat pumps, must be tested to AHRI 1160."
    }
  },
  {
    "id": "WI-87",
    "authority_type": "utility",
    "authority": "wi-east-central-energy",
    "payment_methods": [
      "rebate"
    ],
    "items": [
      "smart_thermostat"
    ],
    "program": "wi_eastCentralEnergy_residentialRebates",
    "amount": {
      "type": "dollar_amount",
      "number": 25
    },
    "owner_status": [
      "homeowner"
    ],
    "short_description": {
      "en": "$25 rebate for Wi-Fi smart thermostats."
    }
  },
  {
    "id": "WI-88",
    "authority_type": "utility",
    "authority": "wi-jackson-electric-cooperative",
    "payment_methods": [
      "account_credit"
    ],
    "items": [
      "heat_pump_clothes_dryer"
    ],
    "program": "wi_jacksonElectricCooperative_rebatesAndIncentives",
    "amount": {
      "type": "dollar_amount",
      "number": 150
    },
    "owner_status": [
      "homeowner"
    ],
    "short_description": {
      "en": "$150 rebate for ENERGY STAR® rated clothes dryers."
    },
    "start_date": "2024-01-01",
    "end_date": "2024-12-31"
  },
  {
    "id": "WI-89",
    "authority_type": "utility",
    "authority": "wi-jackson-electric-cooperative",
    "payment_methods": [
      "account_credit"
    ],
    "items": [
      "electric_stove"
    ],
    "program": "wi_jacksonElectricCooperative_rebatesAndIncentives",
    "amount": {
      "type": "dollar_amount",
      "number": 150
    },
    "owner_status": [
      "homeowner"
    ],
    "short_description": {
      "en": "$150 rebate for ENERGY STAR® rated induction ranges."
    },
    "start_date": "2024-01-01",
    "end_date": "2024-12-31"
  },
  {
    "id": "WI-90",
    "authority_type": "utility",
    "authority": "wi-jackson-electric-cooperative",
    "payment_methods": [
      "rebate"
    ],
    "items": [
      "electric_vehicle_charger"
    ],
    "program": "wi_jacksonElectricCooperative_rebatesAndIncentives",
    "amount": {
      "type": "dollar_amount",
      "number": 800
    },
    "owner_status": [
      "homeowner"
    ],
    "short_description": {
      "en": "$800 rebate for smart EV chargers with integrated metering."
    },
    "start_date": "2024-01-01",
    "end_date": "2024-12-31"
  },
  {
    "id": "WI-91",
    "authority_type": "utility",
    "authority": "wi-jackson-electric-cooperative",
    "payment_methods": [
      "account_credit"
    ],
    "items": [
      "ducted_heat_pump",
      "ductless_heat_pump"
    ],
    "program": "wi_jacksonElectricCooperative_rebatesAndIncentives",
    "amount": {
      "type": "dollars_per_unit",
      "number": 500,
      "unit": "ton"
    },
    "owner_status": [
      "homeowner"
    ],
    "short_description": {
      "en": "$500/ton rebate for air source heat pumps SEER 14+, HSPF 8.2+, or EER 11+."
    },
    "start_date": "2024-01-01",
    "end_date": "2024-12-31"
  },
  {
    "id": "WI-92",
    "authority_type": "utility",
    "authority": "wi-jackson-electric-cooperative",
    "payment_methods": [
      "account_credit"
    ],
    "items": [
      "geothermal_heating_installation"
    ],
    "program": "wi_jacksonElectricCooperative_rebatesAndIncentives",
    "amount": {
      "type": "dollars_per_unit",
      "number": 500,
      "unit": "ton"
    },
    "owner_status": [
      "homeowner"
    ],
    "short_description": {
      "en": "$500/ton rebate for geothermal heat pumps. New units not allowed on load management program."
    },
    "start_date": "2024-01-01",
    "end_date": "2024-12-31"
  },
  {
    "id": "WI-93",
    "authority_type": "utility",
    "authority": "wi-jackson-electric-cooperative",
    "payment_methods": [
      "account_credit"
    ],
    "items": [
      "other_weatherization"
    ],
    "program": "wi_jacksonElectricCooperative_rebatesAndIncentives",
    "amount": {
      "type": "dollar_amount",
      "number": 500
    },
    "owner_status": [
      "homeowner"
    ],
    "short_description": {
      "en": "Up to $500 rebate for energy efficiency improvements. Must be recommendations from an audit arranged by a cooperative approved partner."
    },
    "start_date": "2024-01-01",
    "end_date": "2024-12-31"
  },
  {
    "id": "WI-94",
    "authority_type": "utility",
    "authority": "wi-jackson-electric-cooperative",
    "payment_methods": [
      "account_credit"
    ],
    "items": [
      "non_heat_pump_water_heater"
    ],
    "program": "wi_jacksonElectricCooperative_rebatesAndIncentives",
    "amount": {
      "type": "dollar_amount",
      "number": 300,
      "minimum": 150,
      "maximum": 300
    },
    "owner_status": [
      "homeowner"
    ],
    "short_description": {
      "en": "Up to $300 rebate for water heaters with capacity of at least 75 gallons."
    },
    "start_date": "2024-01-01",
    "end_date": "2024-12-31"
  },
  {
    "id": "WI-95",
    "authority_type": "utility",
    "authority": "wi-jackson-electric-cooperative",
    "payment_methods": [
      "account_credit"
    ],
    "items": [
      "heat_pump_water_heater"
    ],
    "program": "wi_jacksonElectricCooperative_rebatesAndIncentives",
    "amount": {
      "type": "dollar_amount",
      "number": 300
    },
    "owner_status": [
      "homeowner"
    ],
    "short_description": {
      "en": "$300 rebate for integrated heat pump water heaters. UEF 2.00 or greater."
    },
    "start_date": "2024-01-01",
    "end_date": "2024-12-31"
  },
  {
    "id": "WI-97",
    "authority_type": "utility",
    "authority": "wi-pierce-pepin-cooperative-services",
    "payment_methods": [
      "rebate"
    ],
    "items": [
      "electric_vehicle_charger"
    ],
    "program": "wi_piercePepinCooperativeServices_eVChargingStationRebates",
    "amount": {
      "type": "dollar_amount",
      "number": 400
    },
    "owner_status": [
      "homeowner"
    ],
    "short_description": {
      "en": "Up to $400 incentive for EV chargers."
    },
    "end_date": "2024-12-31"
  },
  {
    "id": "WI-98",
    "authority_type": "utility",
    "authority": "wi-pierce-pepin-cooperative-services",
    "payment_methods": [
      "rebate"
    ],
    "items": [
      "electric_vehicle_charger"
    ],
    "program": "wi_piercePepinCooperativeServices_eVChargingStationRebates",
    "amount": {
      "type": "dollar_amount",
      "number": 800
    },
    "owner_status": [
      "homeowner"
    ],
    "short_description": {
      "en": "Up to $800 incentive for smart EV chargers with integrated metering."
    },
    "end_date": "2024-12-31"
  },
  {
    "id": "WI-99",
    "authority_type": "utility",
    "authority": "wi-pierce-pepin-cooperative-services",
    "payment_methods": [
      "rebate"
    ],
    "items": [
      "geothermal_heating_installation"
    ],
    "program": "wi_piercePepinCooperativeServices_hVAC-HeatPumps",
    "amount": {
      "type": "dollars_per_unit",
      "number": 500,
      "unit": "ton"
    },
    "owner_status": [
      "homeowner"
    ],
    "short_description": {
      "en": "$500/ton rebate for geothermal heat pumps."
    },
    "end_date": "2024-12-31"
  },
  {
    "id": "WI-100",
    "authority_type": "utility",
    "authority": "wi-pierce-pepin-cooperative-services",
    "payment_methods": [
      "rebate"
    ],
    "items": [
      "heat_pump_clothes_dryer"
    ],
    "program": "wi_piercePepinCooperativeServices_applianceRebates",
    "amount": {
      "type": "dollar_amount",
      "number": 25
    },
    "owner_status": [
      "homeowner"
    ],
    "short_description": {
      "en": "$25 rebate for ENERGY STAR® clothes dryers."
    },
    "end_date": "2024-12-31"
  },
  {
    "id": "WI-101",
    "authority_type": "utility",
    "authority": "wi-pierce-pepin-cooperative-services",
    "payment_methods": [
      "rebate"
    ],
    "items": [
      "non_heat_pump_water_heater"
    ],
    "program": "wi_piercePepinCooperativeServices_electricWaterHeaterRebates",
    "amount": {
      "type": "dollar_amount",
      "number": 600,
      "minimum": 300,
      "maximum": 600
    },
    "owner_status": [
      "homeowner"
    ],
    "short_description": {
      "en": "Up to $600 incentive for residential high efficiency water heaters, depending on capacity. UEF must be at least .88."
    },
    "end_date": "2024-12-31"
  },
  {
    "id": "WI-102",
    "authority_type": "utility",
    "authority": "wi-pierce-pepin-cooperative-services",
    "payment_methods": [
      "rebate"
    ],
    "items": [
      "heat_pump_water_heater"
    ],
    "program": "wi_piercePepinCooperativeServices_electricWaterHeaterRebates",
    "amount": {
      "type": "dollar_amount",
      "number": 600
    },
    "owner_status": [
      "homeowner"
    ],
    "short_description": {
      "en": "$600 incentive for integrated heat pump water heaters. UEF must be at least 2.20."
    },
    "end_date": "2024-12-31"
  },
  {
    "id": "WI-103",
    "authority_type": "utility",
    "authority": "wi-pierce-pepin-cooperative-services",
    "payment_methods": [
      "rebate"
    ],
    "items": [
      "ducted_heat_pump"
    ],
    "program": "wi_piercePepinCooperativeServices_hVAC-HeatPumps",
    "amount": {
      "type": "dollars_per_unit",
      "number": 300,
      "unit": "ton"
    },
    "owner_status": [
      "homeowner"
    ],
    "short_description": {
      "en": "$300/ton rebate for central ducted air source heat pumps. SEER2 14.3+, HSPF2 7.5+ OR SEER 15+, HSPF 8.8+."
    },
    "end_date": "2024-12-31"
  },
  {
    "id": "WI-104",
    "authority_type": "utility",
    "authority": "wi-pierce-pepin-cooperative-services",
    "payment_methods": [
      "rebate"
    ],
    "items": [
      "ductless_heat_pump"
    ],
    "program": "wi_piercePepinCooperativeServices_hVAC-HeatPumps",
    "amount": {
      "type": "dollars_per_unit",
      "number": 300,
      "unit": "ton"
    },
    "owner_status": [
      "homeowner"
    ],
    "short_description": {
      "en": "$300/ton rebate for ductless mini-split heat pumps. SEER2 14.3+, HSPF2 7.5+ OR SEER 15+, HSPF 8.8+."
    },
    "end_date": "2024-12-31"
  },
  {
    "id": "WI-105",
    "authority_type": "utility",
    "authority": "wi-pierce-pepin-cooperative-services",
    "payment_methods": [
      "rebate"
    ],
    "items": [
      "electric_stove"
    ],
    "program": "wi_piercePepinCooperativeServices_applianceRebates",
    "amount": {
      "type": "dollar_amount",
      "number": 25
    },
    "owner_status": [
      "homeowner"
    ],
    "short_description": {
      "en": "$25 incentive for induction ranges."
    },
    "end_date": "2024-12-31"
  },
  {
    "id": "WI-106",
    "authority_type": "utility",
    "authority": "wi-pierce-pepin-cooperative-services",
    "payment_methods": [
      "rebate"
    ],
    "items": [
      "smart_thermostat"
    ],
    "program": "wi_piercePepinCooperativeServices_hVAC-HeatPumps",
    "amount": {
      "type": "dollar_amount",
      "number": 25
    },
    "owner_status": [
      "homeowner"
    ],
    "short_description": {
      "en": "$25 for smart thermostats enrolled in Load Management Program."
    },
    "end_date": "2024-12-31"
  },
  {
    "id": "WI-107",
    "authority_type": "utility",
    "authority": "wi-pierce-pepin-cooperative-services",
    "payment_methods": [
      "rebate"
    ],
    "items": [
      "other_weatherization"
    ],
    "program": "wi_piercePepinCooperativeServices_energyEfficiencyImprovements",
    "amount": {
      "type": "dollar_amount",
      "number": 500
    },
    "owner_status": [
      "homeowner"
    ],
    "short_description": {
      "en": "Up to $500 for audit-recommended energy efficiency improvements."
    },
    "end_date": "2024-12-31"
  },
  {
    "id": "WI-108",
    "authority_type": "utility",
    "authority": "wi-polk-burnett-electric-cooperative",
    "payment_methods": [
      "rebate"
    ],
    "items": [
      "electric_vehicle_charger"
    ],
    "program": "wi_polk-BurnettElectricCooperative_eVChargerRebates",
    "amount": {
      "type": "dollar_amount",
      "number": 800
    },
    "owner_status": [
      "homeowner"
    ],
    "short_description": {
      "en": "$800 rebate for smart EV chargers with integrated metering."
    },
    "start_date": "2024-01-01",
    "end_date": "2024-12-31"
  },
  {
    "id": "WI-109",
    "authority_type": "utility",
    "authority": "wi-polk-burnett-electric-cooperative",
    "payment_methods": [
      "rebate"
    ],
    "items": [
      "geothermal_heating_installation"
    ],
    "program": "wi_polk-BurnettElectricCooperative_hVACRebates",
    "amount": {
      "type": "dollars_per_unit",
      "number": 500,
      "unit": "ton"
    },
    "owner_status": [
      "homeowner"
    ],
    "short_description": {
      "en": "$500/ton rebate for geothermal heat pumps, may qualify for off-peak rates."
    },
    "start_date": "2024-01-01",
    "end_date": "2024-12-31"
  },
  {
    "id": "WI-110",
    "authority_type": "utility",
    "authority": "wi-polk-burnett-electric-cooperative",
    "payment_methods": [
      "account_credit"
    ],
    "items": [
      "heat_pump_clothes_dryer"
    ],
    "program": "wi_polk-BurnettElectricCooperative_applianceRebates",
    "amount": {
      "type": "dollar_amount",
      "number": 25
    },
    "owner_status": [
      "homeowner"
    ],
    "short_description": {
      "en": "$25 rebate for ENERGY STAR® clothes dryers."
    },
    "start_date": "2024-01-01",
    "end_date": "2024-12-31"
  },
  {
    "id": "WI-111",
    "authority_type": "utility",
    "authority": "wi-polk-burnett-electric-cooperative",
    "payment_methods": [
      "rebate"
    ],
    "items": [
      "heat_pump_water_heater"
    ],
    "program": "wi_polk-BurnettElectricCooperative_waterHeaterRebates",
    "amount": {
      "type": "dollar_amount",
      "number": 300
    },
    "owner_status": [
      "homeowner"
    ],
    "short_description": {
      "en": "$300 rebate for integrated heat pump water heaters with UEF 2.20+."
    },
    "start_date": "2024-01-01",
    "end_date": "2024-12-31"
  },
  {
    "id": "WI-112",
    "authority_type": "utility",
    "authority": "wi-polk-burnett-electric-cooperative",
    "payment_methods": [
      "rebate"
    ],
    "items": [
      "ducted_heat_pump",
      "ductless_heat_pump"
    ],
    "program": "wi_polk-BurnettElectricCooperative_hVACRebates",
    "amount": {
      "type": "dollars_per_unit",
      "number": 300,
      "unit": "ton"
    },
    "owner_status": [
      "homeowner"
    ],
    "short_description": {
      "en": "$300/ton rebate for air source & mini-split heat pumps, SEER2 14.3+, HSPF2 7.5+."
    },
    "start_date": "2024-01-01",
    "end_date": "2024-12-31"
  },
  {
    "id": "WI-113",
    "authority_type": "utility",
    "authority": "wi-polk-burnett-electric-cooperative",
    "payment_methods": [
      "account_credit"
    ],
    "items": [
      "electric_stove"
    ],
    "program": "wi_polk-BurnettElectricCooperative_applianceRebates",
    "amount": {
      "type": "dollar_amount",
      "number": 25
    },
    "owner_status": [
      "homeowner"
    ],
    "short_description": {
      "en": "$25 rebate for induction ranges."
    },
    "start_date": "2024-01-01",
    "end_date": "2024-12-31"
  },
  {
    "id": "WI-114",
    "authority_type": "utility",
    "authority": "wi-polk-burnett-electric-cooperative",
    "payment_methods": [
      "rebate"
    ],
    "items": [
      "rooftop_solar_installation"
    ],
    "program": "wi_polk-BurnettElectricCooperative_renewableSolarRebates",
    "amount": {
      "type": "dollars_per_unit",
      "number": 200,
      "unit": "kilowatt",
      "maximum": 600
    },
    "owner_status": [
      "homeowner"
    ],
    "short_description": {
      "en": "$200/kW solar PV rebate, capped at $600 per account."
    },
    "start_date": "2024-01-01",
    "end_date": "2024-12-31"
  },
  {
    "id": "WI-115",
    "authority_type": "utility",
    "authority": "wi-polk-burnett-electric-cooperative",
    "payment_methods": [
      "rebate"
    ],
    "items": [
      "air_sealing"
    ],
    "program": "wi_polk-BurnettElectricCooperative_homeImprovementMeasureRebates",
    "amount": {
      "type": "percent",
      "number": 0.3,
      "maximum": 1000
    },
    "owner_status": [
      "homeowner"
    ],
    "short_description": {
      "en": "30% of cost for air infiltration reduction measures, up to $1,000."
    },
    "end_date": "2024-12-31"
  },
  {
    "id": "WI-116",
    "authority_type": "utility",
    "authority": "wi-price-electric-cooperative",
    "payment_methods": [
      "rebate"
    ],
    "items": [
      "geothermal_heating_installation"
    ],
    "program": "wi_priceElectricCooperative_pECSmartSenseRebates:HVAC",
    "amount": {
      "type": "dollars_per_unit",
      "number": 600,
      "unit": "ton"
    },
    "owner_status": [
      "homeowner"
    ],
    "short_description": {
      "en": "Up to $600/ton for geothermal heat pumps."
    },
    "end_date": "2024-12-31"
  },
  {
    "id": "WI-117",
    "authority_type": "utility",
    "authority": "wi-price-electric-cooperative",
    "payment_methods": [
      "rebate"
    ],
    "items": [
      "heat_pump_clothes_dryer"
    ],
    "program": "wi_priceElectricCooperative_pECSmartSenseRebates:Appliances",
    "amount": {
      "type": "dollar_amount",
      "number": 50
    },
    "owner_status": [
      "homeowner"
    ],
    "short_description": {
      "en": "$50 rebate for ENERGY STAR® clothes dryers."
    },
    "end_date": "2024-12-31"
  },
  {
    "id": "WI-118",
    "authority_type": "utility",
    "authority": "wi-price-electric-cooperative",
    "payment_methods": [
      "rebate"
    ],
    "items": [
      "non_heat_pump_water_heater"
    ],
    "program": "wi_priceElectricCooperative_pECSmartSenseRebates:WaterHeaters",
    "amount": {
      "type": "dollar_amount",
      "number": 1000,
      "minimum": 150,
      "maximum": 1000
    },
    "owner_status": [
      "homeowner"
    ],
    "short_description": {
      "en": "Up to $1,000 rebate for water heaters, depending on capacity and efficiency. Must be load controlled."
    },
    "end_date": "2024-12-31"
  },
  {
    "id": "WI-119",
    "authority_type": "utility",
    "authority": "wi-price-electric-cooperative",
    "payment_methods": [
      "rebate"
    ],
    "items": [
      "heat_pump_water_heater"
    ],
    "program": "wi_priceElectricCooperative_pECSmartSenseRebates:WaterHeaters",
    "amount": {
      "type": "dollar_amount",
      "number": 300
    },
    "owner_status": [
      "homeowner"
    ],
    "short_description": {
      "en": "$300 rebate for integrated heat pump water heaters. UEF must be at least 2.2."
    },
    "end_date": "2024-12-31"
  },
  {
    "id": "WI-120",
    "authority_type": "utility",
    "authority": "wi-price-electric-cooperative",
    "payment_methods": [
      "rebate"
    ],
    "items": [
      "ducted_heat_pump",
      "ductless_heat_pump"
    ],
    "program": "wi_priceElectricCooperative_pECSmartSenseRebates:HVAC",
    "amount": {
      "type": "dollars_per_unit",
      "number": 400,
      "unit": "ton"
    },
    "owner_status": [
      "homeowner"
    ],
    "short_description": {
      "en": "Up to $400/ton for air source & mini-split heat pumps with SEER2 14.3+ or SEER 15+."
    },
    "end_date": "2024-12-31"
  },
  {
    "id": "WI-121",
    "authority_type": "utility",
    "authority": "wi-price-electric-cooperative",
    "payment_methods": [
      "rebate"
    ],
    "items": [
      "electric_stove"
    ],
    "program": "wi_priceElectricCooperative_pECSmartSenseRebates:Appliances",
    "amount": {
      "type": "dollar_amount",
      "number": 50
    },
    "owner_status": [
      "homeowner"
    ],
    "short_description": {
      "en": "$50 rebate for induction ranges."
    },
    "end_date": "2024-12-31"
  },
  {
    "id": "WI-122",
    "authority_type": "utility",
    "authority": "wi-price-electric-cooperative",
    "payment_methods": [
      "rebate"
    ],
    "items": [
      "rooftop_solar_installation"
    ],
    "program": "wi_priceElectricCooperative_pECSmartSenseRebates:Solar",
    "amount": {
      "type": "dollar_amount",
      "number": 500
    },
    "owner_status": [
      "homeowner"
    ],
    "short_description": {
      "en": "$500 incentive for qualified Solar Electric (PV) System installations."
    },
    "start_date": "2024-01-01",
    "end_date": "2024-12-31"
  },
  {
    "id": "WI-123",
    "authority_type": "utility",
    "authority": "wi-price-electric-cooperative",
    "payment_methods": [
      "rebate"
    ],
    "items": [
      "smart_thermostat"
    ],
    "program": "wi_priceElectricCooperative_pECSmartSenseRebates:HVAC",
    "amount": {
      "type": "dollar_amount",
      "number": 75
    },
    "owner_status": [
      "homeowner"
    ],
    "short_description": {
      "en": "$75 incentive for WiFi enabled smart thermostats."
    },
    "end_date": "2024-12-31"
  },
  {
    "id": "WI-124",
    "authority_type": "utility",
    "authority": "wi-price-electric-cooperative",
    "payment_methods": [
      "rebate"
    ],
    "items": [
      "other_weatherization"
    ],
    "program": "wi_priceElectricCooperative_pECSmartSenseRebates:EnergyAudit-RecommendedImprovements",
    "amount": {
      "type": "dollar_amount",
      "number": 500
    },
    "owner_status": [
      "homeowner"
    ],
    "short_description": {
      "en": "Up to $500 for audit-recommended energy efficiency improvements."
    },
    "end_date": "2024-12-31"
  },
  {
    "id": "WI-125",
    "authority_type": "utility",
    "authority": "wi-riverland-energy-cooperative",
    "payment_methods": [
      "rebate"
    ],
    "items": [
      "electric_vehicle_charger"
    ],
    "program": "wi_riverlandEnergyCooperative_eVChargingRebates",
    "amount": {
      "type": "dollar_amount",
      "number": 400
    },
    "owner_status": [
      "homeowner"
    ],
    "short_description": {
      "en": "$400 rebate for EV chargers with load control."
    },
    "end_date": "2024-12-31"
  },
  {
    "id": "WI-126",
    "authority_type": "utility",
    "authority": "wi-riverland-energy-cooperative",
    "payment_methods": [
      "rebate"
    ],
    "items": [
      "electric_vehicle_charger"
    ],
    "program": "wi_riverlandEnergyCooperative_eVChargingRebates",
    "amount": {
      "type": "dollar_amount",
      "number": 800
    },
    "owner_status": [
      "homeowner"
    ],
    "short_description": {
      "en": "$800 rebate for smart EV chargers with integrated metering and load control."
    },
    "end_date": "2024-12-31"
  },
  {
    "id": "WI-127",
    "authority_type": "utility",
    "authority": "wi-riverland-energy-cooperative",
    "payment_methods": [
      "rebate"
    ],
    "items": [
      "geothermal_heating_installation"
    ],
    "program": "wi_riverlandEnergyCooperative_hVACRebates",
    "amount": {
      "type": "dollars_per_unit",
      "number": 500,
      "unit": "ton"
    },
    "owner_status": [
      "homeowner"
    ],
    "short_description": {
      "en": "$500/ton rebate for geothermal heat pumps."
    },
    "end_date": "2024-12-31"
  },
  {
    "id": "WI-128",
    "authority_type": "utility",
    "authority": "wi-riverland-energy-cooperative",
    "payment_methods": [
      "rebate"
    ],
    "items": [
      "heat_pump_clothes_dryer"
    ],
    "program": "wi_riverlandEnergyCooperative_applianceRebates",
    "amount": {
      "type": "dollar_amount",
      "number": 25
    },
    "owner_status": [
      "homeowner"
    ],
    "short_description": {
      "en": "$25 rebate for ENERGY STAR® clothes dryers."
    },
    "end_date": "2024-12-31"
  },
  {
    "id": "WI-129",
    "authority_type": "utility",
    "authority": "wi-riverland-energy-cooperative",
    "payment_methods": [
      "rebate"
    ],
    "items": [
      "non_heat_pump_water_heater"
    ],
    "program": "wi_riverlandEnergyCooperative_waterHeaterRebates",
    "amount": {
      "type": "dollar_amount",
      "number": 300,
      "minimum": 150,
      "maximum": 300
    },
    "owner_status": [
      "homeowner"
    ],
    "short_description": {
      "en": "Up to $300 rebate for residential high efficiency water heaters, depending on capacity. UEF must be at least .88."
    },
    "end_date": "2024-12-31"
  },
  {
    "id": "WI-130",
    "authority_type": "utility",
    "authority": "wi-riverland-energy-cooperative",
    "payment_methods": [
      "rebate"
    ],
    "items": [
      "heat_pump_water_heater"
    ],
    "program": "wi_riverlandEnergyCooperative_waterHeaterRebates",
    "amount": {
      "type": "dollar_amount",
      "number": 300
    },
    "owner_status": [
      "homeowner"
    ],
    "short_description": {
      "en": "$300 rebate for integrated heat pump water heaters, UEF at least 2.00, controlled by Cooperative's load control program."
    },
    "end_date": "2024-12-31"
  },
  {
    "id": "WI-131",
    "authority_type": "utility",
    "authority": "wi-riverland-energy-cooperative",
    "payment_methods": [
      "rebate"
    ],
    "items": [
      "ducted_heat_pump",
      "ductless_heat_pump"
    ],
    "program": "wi_riverlandEnergyCooperative_hVACRebates",
    "amount": {
      "type": "dollars_per_unit",
      "number": 300,
      "unit": "ton"
    },
    "owner_status": [
      "homeowner"
    ],
    "short_description": {
      "en": "$300 rebate for air source & mini-split heat pumps. SEER2 14.3+, HSPF2 7.5+ or SEER 15+, HSPF 8.8+."
    },
    "end_date": "2024-12-31"
  },
  {
    "id": "WI-132",
    "authority_type": "utility",
    "authority": "wi-riverland-energy-cooperative",
    "payment_methods": [
      "rebate"
    ],
    "items": [
      "electric_stove"
    ],
    "program": "wi_riverlandEnergyCooperative_applianceRebates",
    "amount": {
      "type": "dollar_amount",
      "number": 25
    },
    "owner_status": [
      "homeowner"
    ],
    "short_description": {
      "en": "$25 rebate for ENERGY STAR® induction ranges."
    },
    "end_date": "2024-12-31"
  },
  {
    "id": "WI-135",
    "authority_type": "other",
    "authority": "wi-focus-on-energy",
    "eligible_geo_group": "wi-group-focus-on-energy",
    "payment_methods": [
      "rebate"
    ],
    "items": [
      "ducted_heat_pump",
      "ductless_heat_pump"
    ],
    "program": "wi_focusOnEnergy_heating&CoolingRebates",
    "amount": {
      "type": "dollar_amount",
      "number": 1300
    },
    "owner_status": [
      "homeowner",
      "renter"
    ],
    "short_description": {
      "en": "$1,300 rebate for cold climate air source heat pumps replacing natural gas or electric resistance."
    },
    "start_date": "2024-01-01",
    "end_date": "2024-05-31"
  },
  {
    "id": "WI-136",
    "authority_type": "other",
    "authority": "wi-focus-on-energy",
    "eligible_geo_group": "wi-group-focus-on-energy",
    "payment_methods": [
      "rebate"
    ],
    "items": [
      "ducted_heat_pump",
      "ductless_heat_pump"
    ],
    "program": "wi_focusOnEnergy_heating&CoolingRebates",
    "amount": {
      "type": "dollar_amount",
      "number": 500
    },
    "owner_status": [
      "homeowner",
      "renter"
    ],
    "short_description": {
      "en": "$500 rebate for cold climate air source heat pumps replacing propane, oil, existing heat pump, etc."
    },
    "start_date": "2024-01-01",
    "end_date": "2024-05-31"
  }
]
